{
  "module_version": "3.0", 
  "skip_undocumented": true, 
  "author": "Dropbox, Inc.", 
  "module": "ObjectiveDropboxOfficial", 
  "custom_categories": [
    {
      "name": "Async", 
      "children": [
        "DBASYNCLaunchResultBase", 
        "DBASYNCLaunchEmptyResult", 
        "DBASYNCPollArg", 
        "DBASYNCPollResultBase", 
        "DBASYNCPollEmptyResult", 
        "DBASYNCPollError"
      ]
    }, 
    {
      "name": "Auth", 
      "children": [
        "DBAUTHAccessError", 
        "DBAUTHAuthError", 
        "DBAUTHInvalidAccountTypeError", 
        "DBAUTHPaperAccessError", 
        "DBAUTHRateLimitError", 
        "DBAUTHRateLimitReason", 
        "DBAUTHTokenFromOAuth1Arg", 
        "DBAUTHTokenFromOAuth1Error", 
        "DBAUTHTokenFromOAuth1Result"
      ]
    }, 
    {
      "name": "Common", 
      "children": [
        "DBCOMMONInvalidPathRootError", 
        "DBCOMMONPathRoot", 
        "DBCOMMONPathRootError"
      ]
    }, 
    {
      "name": "Files", 
      "children": [
        "DBFILESPropertiesError", 
        "DBFILESInvalidPropertyGroupError", 
        "DBFILESAddPropertiesError", 
        "DBFILESGetMetadataArg", 
        "DBFILESAlphaGetMetadataArg", 
        "DBFILESGetMetadataError", 
        "DBFILESAlphaGetMetadataError", 
        "DBFILESCommitInfo", 
        "DBFILESCommitInfoWithProperties", 
        "DBFILESCreateFolderArg", 
        "DBFILESCreateFolderError", 
        "DBFILESDeleteArg", 
        "DBFILESDeleteBatchArg", 
        "DBFILESDeleteBatchError", 
        "DBFILESDeleteBatchJobStatus", 
        "DBFILESDeleteBatchLaunch", 
        "DBFILESDeleteBatchResult", 
        "DBFILESDeleteBatchResultEntry", 
        "DBFILESDeleteError", 
        "DBFILESDeleteResult", 
        "DBFILESMetadata", 
        "DBFILESDeletedMetadata", 
        "DBFILESDimensions", 
        "DBFILESDownloadArg", 
        "DBFILESDownloadError", 
        "DBFILESFileMetadata", 
        "DBFILESSharingInfo", 
        "DBFILESFileSharingInfo", 
        "DBFILESFolderMetadata", 
        "DBFILESFolderSharingInfo", 
        "DBFILESGetCopyReferenceArg", 
        "DBFILESGetCopyReferenceError", 
        "DBFILESGetCopyReferenceResult", 
        "DBFILESGetTemporaryLinkArg", 
        "DBFILESGetTemporaryLinkError", 
        "DBFILESGetTemporaryLinkResult", 
        "DBFILESGpsCoordinates", 
        "DBFILESListFolderArg", 
        "DBFILESListFolderContinueArg", 
        "DBFILESListFolderContinueError", 
        "DBFILESListFolderError", 
        "DBFILESListFolderGetLatestCursorResult", 
        "DBFILESListFolderLongpollArg", 
        "DBFILESListFolderLongpollError", 
        "DBFILESListFolderLongpollResult", 
        "DBFILESListFolderResult", 
        "DBFILESListRevisionsArg", 
        "DBFILESListRevisionsError", 
        "DBFILESListRevisionsResult", 
        "DBFILESLookUpPropertiesError", 
        "DBFILESLookupError", 
        "DBFILESMediaInfo", 
        "DBFILESMediaMetadata", 
        "DBFILESPhotoMetadata", 
        "DBFILESPreviewArg", 
        "DBFILESPreviewError", 
        "DBFILESPropertyGroupUpdate", 
        "DBFILESPropertyGroupWithPath", 
        "DBFILESRelocationPath", 
        "DBFILESRelocationArg", 
        "DBFILESRelocationBatchArg", 
        "DBFILESRelocationError", 
        "DBFILESRelocationBatchError", 
        "DBFILESRelocationBatchJobStatus", 
        "DBFILESRelocationBatchLaunch", 
        "DBFILESRelocationBatchResult", 
        "DBFILESRelocationResult", 
        "DBFILESRemovePropertiesArg", 
        "DBFILESRemovePropertiesError", 
        "DBFILESRestoreArg", 
        "DBFILESRestoreError", 
        "DBFILESSaveCopyReferenceArg", 
        "DBFILESSaveCopyReferenceError", 
        "DBFILESSaveCopyReferenceResult", 
        "DBFILESSaveUrlArg", 
        "DBFILESSaveUrlError", 
        "DBFILESSaveUrlJobStatus", 
        "DBFILESSaveUrlResult", 
        "DBFILESSearchArg", 
        "DBFILESSearchError", 
        "DBFILESSearchMatch", 
        "DBFILESSearchMatchType", 
        "DBFILESSearchMode", 
        "DBFILESSearchResult", 
        "DBFILESThumbnailArg", 
        "DBFILESThumbnailError", 
        "DBFILESThumbnailFormat", 
        "DBFILESThumbnailSize", 
        "DBFILESUpdatePropertiesError", 
        "DBFILESUpdatePropertyGroupArg", 
        "DBFILESUploadError", 
        "DBFILESUploadErrorWithProperties", 
        "DBFILESUploadSessionAppendArg", 
        "DBFILESUploadSessionCursor", 
        "DBFILESUploadSessionFinishArg", 
        "DBFILESUploadSessionFinishBatchArg", 
        "DBFILESUploadSessionFinishBatchJobStatus", 
        "DBFILESUploadSessionFinishBatchLaunch", 
        "DBFILESUploadSessionFinishBatchResult", 
        "DBFILESUploadSessionFinishBatchResultEntry", 
        "DBFILESUploadSessionFinishError", 
        "DBFILESUploadSessionLookupError", 
        "DBFILESUploadSessionOffsetError", 
        "DBFILESUploadSessionStartArg", 
        "DBFILESUploadSessionStartResult", 
        "DBFILESUploadWriteFailed", 
        "DBFILESVideoMetadata", 
        "DBFILESWriteConflictError", 
        "DBFILESWriteError", 
        "DBFILESWriteMode"
      ]
    }, 
    {
      "name": "Paper", 
      "children": [
        "DBPAPERAddMember", 
        "DBPAPERRefPaperDoc", 
        "DBPAPERAddPaperDocUser", 
        "DBPAPERAddPaperDocUserMemberResult", 
        "DBPAPERAddPaperDocUserResult", 
        "DBPAPERCursor", 
        "DBPAPERPaperApiBaseError", 
        "DBPAPERDocLookupError", 
        "DBPAPERDocSubscriptionLevel", 
        "DBPAPERExportFormat", 
        "DBPAPERFolder", 
        "DBPAPERFolderSharingPolicyType", 
        "DBPAPERFolderSubscriptionLevel", 
        "DBPAPERFoldersContainingPaperDoc", 
        "DBPAPERInviteeInfoWithPermissionLevel", 
        "DBPAPERListDocsCursorError", 
        "DBPAPERListPaperDocsArgs", 
        "DBPAPERListPaperDocsContinueArgs", 
        "DBPAPERListPaperDocsFilterBy", 
        "DBPAPERListPaperDocsResponse", 
        "DBPAPERListPaperDocsSortBy", 
        "DBPAPERListPaperDocsSortOrder", 
        "DBPAPERListUsersCursorError", 
        "DBPAPERListUsersOnFolderArgs", 
        "DBPAPERListUsersOnFolderContinueArgs", 
        "DBPAPERListUsersOnFolderResponse", 
        "DBPAPERListUsersOnPaperDocArgs", 
        "DBPAPERListUsersOnPaperDocContinueArgs", 
        "DBPAPERListUsersOnPaperDocResponse", 
        "DBPAPERPaperApiCursorError", 
        "DBPAPERPaperDocExport", 
        "DBPAPERPaperDocExportResult", 
        "DBPAPERPaperDocPermissionLevel", 
        "DBPAPERPaperDocSharingPolicy", 
        "DBPAPERRemovePaperDocUser", 
        "DBPAPERSharingPolicy", 
        "DBPAPERSharingTeamPolicyType", 
        "DBPAPERSharingPublicPolicyType", 
        "DBPAPERUserInfoWithPermissionLevel", 
        "DBPAPERUserOnPaperDocFilter"
      ]
    }, 
    {
      "name": "Properties", 
      "children": [
        "DBPROPERTIESGetPropertyTemplateArg", 
        "DBPROPERTIESPropertyGroupTemplate", 
        "DBPROPERTIESGetPropertyTemplateResult", 
        "DBPROPERTIESListPropertyTemplateIds", 
        "DBPROPERTIESPropertyTemplateError", 
        "DBPROPERTIESModifyPropertyTemplateError", 
        "DBPROPERTIESPropertyField", 
        "DBPROPERTIESPropertyFieldTemplate", 
        "DBPROPERTIESPropertyGroup", 
        "DBPROPERTIESPropertyType"
      ]
    }, 
    {
      "name": "Sharing", 
      "children": [
        "DBSHARINGAccessLevel", 
        "DBSHARINGAclUpdatePolicy", 
        "DBSHARINGAddFileMemberArgs", 
        "DBSHARINGAddFileMemberError", 
        "DBSHARINGAddFolderMemberArg", 
        "DBSHARINGAddFolderMemberError", 
        "DBSHARINGAddMember", 
        "DBSHARINGAddMemberSelectorError", 
        "DBSHARINGAudienceRestrictingSharedFolder", 
        "DBSHARINGChangeFileMemberAccessArgs", 
        "DBSHARINGLinkMetadata", 
        "DBSHARINGCollectionLinkMetadata", 
        "DBSHARINGCreateSharedLinkArg", 
        "DBSHARINGCreateSharedLinkError", 
        "DBSHARINGCreateSharedLinkWithSettingsArg", 
        "DBSHARINGCreateSharedLinkWithSettingsError", 
        "DBSHARINGSharedContentLinkMetadataBase", 
        "DBSHARINGExpectedSharedContentLinkMetadata", 
        "DBSHARINGFileAction", 
        "DBSHARINGFileErrorResult", 
        "DBSHARINGSharedLinkMetadata", 
        "DBSHARINGFileLinkMetadata", 
        "DBSHARINGFileMemberActionError", 
        "DBSHARINGFileMemberActionIndividualResult", 
        "DBSHARINGFileMemberActionResult", 
        "DBSHARINGFileMemberRemoveActionResult", 
        "DBSHARINGFilePermission", 
        "DBSHARINGFolderAction", 
        "DBSHARINGFolderLinkMetadata", 
        "DBSHARINGFolderPermission", 
        "DBSHARINGFolderPolicy", 
        "DBSHARINGGetFileMetadataArg", 
        "DBSHARINGGetFileMetadataBatchArg", 
        "DBSHARINGGetFileMetadataBatchResult", 
        "DBSHARINGGetFileMetadataError", 
        "DBSHARINGGetFileMetadataIndividualResult", 
        "DBSHARINGGetMetadataArgs", 
        "DBSHARINGSharedLinkError", 
        "DBSHARINGGetSharedLinkFileError", 
        "DBSHARINGGetSharedLinkMetadataArg", 
        "DBSHARINGGetSharedLinksArg", 
        "DBSHARINGGetSharedLinksError", 
        "DBSHARINGGetSharedLinksResult", 
        "DBSHARINGGroupInfo", 
        "DBSHARINGMembershipInfo", 
        "DBSHARINGGroupMembershipInfo", 
        "DBSHARINGInsufficientQuotaAmounts", 
        "DBSHARINGInviteeInfo", 
        "DBSHARINGInviteeMembershipInfo", 
        "DBSHARINGJobError", 
        "DBSHARINGJobStatus", 
        "DBSHARINGLinkAction", 
        "DBSHARINGLinkAudience", 
        "DBSHARINGLinkExpiry", 
        "DBSHARINGLinkPassword", 
        "DBSHARINGLinkPermission", 
        "DBSHARINGLinkPermissions", 
        "DBSHARINGLinkSettings", 
        "DBSHARINGListFileMembersArg", 
        "DBSHARINGListFileMembersBatchArg", 
        "DBSHARINGListFileMembersBatchResult", 
        "DBSHARINGListFileMembersContinueArg", 
        "DBSHARINGListFileMembersContinueError", 
        "DBSHARINGListFileMembersCountResult", 
        "DBSHARINGListFileMembersError", 
        "DBSHARINGListFileMembersIndividualResult", 
        "DBSHARINGListFilesArg", 
        "DBSHARINGListFilesContinueArg", 
        "DBSHARINGListFilesContinueError", 
        "DBSHARINGListFilesResult", 
        "DBSHARINGListFolderMembersCursorArg", 
        "DBSHARINGListFolderMembersArgs", 
        "DBSHARINGListFolderMembersContinueArg", 
        "DBSHARINGListFolderMembersContinueError", 
        "DBSHARINGListFoldersArgs", 
        "DBSHARINGListFoldersContinueArg", 
        "DBSHARINGListFoldersContinueError", 
        "DBSHARINGListFoldersResult", 
        "DBSHARINGListSharedLinksArg", 
        "DBSHARINGListSharedLinksError", 
        "DBSHARINGListSharedLinksResult", 
        "DBSHARINGMemberAccessLevelResult", 
        "DBSHARINGMemberAction", 
        "DBSHARINGMemberPermission", 
        "DBSHARINGMemberPolicy", 
        "DBSHARINGMemberSelector", 
        "DBSHARINGModifySharedLinkSettingsArgs", 
        "DBSHARINGModifySharedLinkSettingsError", 
        "DBSHARINGMountFolderArg", 
        "DBSHARINGMountFolderError", 
        "DBSHARINGParentFolderAccessInfo", 
        "DBSHARINGPathLinkMetadata", 
        "DBSHARINGPendingUploadMode", 
        "DBSHARINGPermissionDeniedReason", 
        "DBSHARINGRelinquishFileMembershipArg", 
        "DBSHARINGRelinquishFileMembershipError", 
        "DBSHARINGRelinquishFolderMembershipArg", 
        "DBSHARINGRelinquishFolderMembershipError", 
        "DBSHARINGRemoveFileMemberArg", 
        "DBSHARINGRemoveFileMemberError", 
        "DBSHARINGRemoveFolderMemberArg", 
        "DBSHARINGRemoveFolderMemberError", 
        "DBSHARINGRemoveMemberJobStatus", 
        "DBSHARINGRequestedVisibility", 
        "DBSHARINGResolvedVisibility", 
        "DBSHARINGRevokeSharedLinkArg", 
        "DBSHARINGRevokeSharedLinkError", 
        "DBSHARINGShareFolderArg", 
        "DBSHARINGShareFolderErrorBase", 
        "DBSHARINGShareFolderError", 
        "DBSHARINGShareFolderJobStatus", 
        "DBSHARINGShareFolderLaunch", 
        "DBSHARINGSharePathError", 
        "DBSHARINGSharedContentLinkMetadata", 
        "DBSHARINGSharedFileMembers", 
        "DBSHARINGSharedFileMetadata", 
        "DBSHARINGSharedFolderAccessError", 
        "DBSHARINGSharedFolderMemberError", 
        "DBSHARINGSharedFolderMembers", 
        "DBSHARINGSharedFolderMetadataBase", 
        "DBSHARINGSharedFolderMetadata", 
        "DBSHARINGSharedLinkAccessFailureReason", 
        "DBSHARINGSharedLinkPolicy", 
        "DBSHARINGSharedLinkSettings", 
        "DBSHARINGSharedLinkSettingsError", 
        "DBSHARINGSharingFileAccessError", 
        "DBSHARINGSharingUserError", 
        "DBSHARINGTeamMemberInfo", 
        "DBSHARINGTransferFolderArg", 
        "DBSHARINGTransferFolderError", 
        "DBSHARINGUnmountFolderArg", 
        "DBSHARINGUnmountFolderError", 
        "DBSHARINGUnshareFileArg", 
        "DBSHARINGUnshareFileError", 
        "DBSHARINGUnshareFolderArg", 
        "DBSHARINGUnshareFolderError", 
        "DBSHARINGUpdateFileMemberArgs", 
        "DBSHARINGUpdateFolderMemberArg", 
        "DBSHARINGUpdateFolderMemberError", 
        "DBSHARINGUpdateFolderPolicyArg", 
        "DBSHARINGUpdateFolderPolicyError", 
        "DBSHARINGUserInfo", 
        "DBSHARINGUserMembershipInfo", 
        "DBSHARINGViewerInfoPolicy", 
        "DBSHARINGVisibility"
      ]
    }, 
    {
      "name": "Team", 
      "children": [
        "DBTEAMDeviceSession", 
        "DBTEAMActiveWebSession", 
        "DBTEAMAddPropertyTemplateArg", 
        "DBTEAMAddPropertyTemplateResult", 
        "DBTEAMAdminTier", 
        "DBTEAMApiApp", 
        "DBTEAMBaseDfbReport", 
        "DBTEAMBaseTeamFolderError", 
        "DBTEAMDateRange", 
        "DBTEAMDateRangeError", 
        "DBTEAMDesktopClientSession", 
        "DBTEAMDesktopPlatform", 
        "DBTEAMDeviceSessionArg", 
        "DBTEAMDevicesActive", 
        "DBTEAMFeature", 
        "DBTEAMFeatureValue", 
        "DBTEAMFeaturesGetValuesBatchArg", 
        "DBTEAMFeaturesGetValuesBatchError", 
        "DBTEAMFeaturesGetValuesBatchResult", 
        "DBTEAMGetActivityReport", 
        "DBTEAMGetDevicesReport", 
        "DBTEAMGetMembershipReport", 
        "DBTEAMGetStorageReport", 
        "DBTEAMGroupAccessType", 
        "DBTEAMGroupCreateArg", 
        "DBTEAMGroupCreateError", 
        "DBTEAMGroupSelectorError", 
        "DBTEAMGroupSelectorWithTeamGroupError", 
        "DBTEAMGroupDeleteError", 
        "DBTEAMGroupFullInfo", 
        "DBTEAMGroupMemberInfo", 
        "DBTEAMGroupMemberSelector", 
        "DBTEAMGroupMemberSelectorError", 
        "DBTEAMGroupMemberSetAccessTypeError", 
        "DBTEAMIncludeMembersArg", 
        "DBTEAMGroupMembersAddArg", 
        "DBTEAMGroupMembersAddError", 
        "DBTEAMGroupMembersChangeResult", 
        "DBTEAMGroupMembersRemoveArg", 
        "DBTEAMGroupMembersSelectorError", 
        "DBTEAMGroupMembersRemoveError", 
        "DBTEAMGroupMembersSelector", 
        "DBTEAMGroupMembersSetAccessTypeArg", 
        "DBTEAMGroupSelector", 
        "DBTEAMGroupUpdateArgs", 
        "DBTEAMGroupUpdateError", 
        "DBTEAMGroupsGetInfoError", 
        "DBTEAMGroupsGetInfoItem", 
        "DBTEAMGroupsListArg", 
        "DBTEAMGroupsListContinueArg", 
        "DBTEAMGroupsListContinueError", 
        "DBTEAMGroupsListResult", 
        "DBTEAMGroupsMembersListArg", 
        "DBTEAMGroupsMembersListContinueArg", 
        "DBTEAMGroupsMembersListContinueError", 
        "DBTEAMGroupsMembersListResult", 
        "DBTEAMGroupsPollError", 
        "DBTEAMGroupsSelector", 
        "DBTEAMListMemberAppsArg", 
        "DBTEAMListMemberAppsError", 
        "DBTEAMListMemberAppsResult", 
        "DBTEAMListMemberDevicesArg", 
        "DBTEAMListMemberDevicesError", 
        "DBTEAMListMemberDevicesResult", 
        "DBTEAMListMembersAppsArg", 
        "DBTEAMListMembersAppsError", 
        "DBTEAMListMembersAppsResult", 
        "DBTEAMListMembersDevicesArg", 
        "DBTEAMListMembersDevicesError", 
        "DBTEAMListMembersDevicesResult", 
        "DBTEAMListTeamAppsArg", 
        "DBTEAMListTeamAppsError", 
        "DBTEAMListTeamAppsResult", 
        "DBTEAMListTeamDevicesArg", 
        "DBTEAMListTeamDevicesError", 
        "DBTEAMListTeamDevicesResult", 
        "DBTEAMMemberAccess", 
        "DBTEAMMemberAddArg", 
        "DBTEAMMemberAddResult", 
        "DBTEAMMemberDevices", 
        "DBTEAMMemberLinkedApps", 
        "DBTEAMMemberProfile", 
        "DBTEAMUserSelectorError", 
        "DBTEAMMemberSelectorError", 
        "DBTEAMMembersAddArg", 
        "DBTEAMMembersAddJobStatus", 
        "DBTEAMMembersAddLaunch", 
        "DBTEAMMembersDeactivateArg", 
        "DBTEAMMembersDeactivateError", 
        "DBTEAMMembersGetInfoArgs", 
        "DBTEAMMembersGetInfoError", 
        "DBTEAMMembersGetInfoItem", 
        "DBTEAMMembersListArg", 
        "DBTEAMMembersListContinueArg", 
        "DBTEAMMembersListContinueError", 
        "DBTEAMMembersListError", 
        "DBTEAMMembersListResult", 
        "DBTEAMMembersRecoverArg", 
        "DBTEAMMembersRecoverError", 
        "DBTEAMMembersRemoveArg", 
        "DBTEAMMembersRemoveError", 
        "DBTEAMMembersSendWelcomeError", 
        "DBTEAMMembersSetPermissionsArg", 
        "DBTEAMMembersSetPermissionsError", 
        "DBTEAMMembersSetPermissionsResult", 
        "DBTEAMMembersSetProfileArg", 
        "DBTEAMMembersSetProfileError", 
        "DBTEAMMembersSuspendError", 
        "DBTEAMMembersUnsuspendArg", 
        "DBTEAMMembersUnsuspendError", 
        "DBTEAMMobileClientPlatform", 
        "DBTEAMMobileClientSession", 
        "DBTEAMRemovedStatus", 
        "DBTEAMRevokeDesktopClientArg", 
        "DBTEAMRevokeDeviceSessionArg", 
        "DBTEAMRevokeDeviceSessionBatchArg", 
        "DBTEAMRevokeDeviceSessionBatchError", 
        "DBTEAMRevokeDeviceSessionBatchResult", 
        "DBTEAMRevokeDeviceSessionError", 
        "DBTEAMRevokeDeviceSessionStatus", 
        "DBTEAMRevokeLinkedApiAppArg", 
        "DBTEAMRevokeLinkedApiAppBatchArg", 
        "DBTEAMRevokeLinkedAppBatchError", 
        "DBTEAMRevokeLinkedAppBatchResult", 
        "DBTEAMRevokeLinkedAppError", 
        "DBTEAMRevokeLinkedAppStatus", 
        "DBTEAMStorageBucket", 
        "DBTEAMTeamFolderAccessError", 
        "DBTEAMTeamFolderActivateError", 
        "DBTEAMTeamFolderIdArg", 
        "DBTEAMTeamFolderArchiveArg", 
        "DBTEAMTeamFolderArchiveError", 
        "DBTEAMTeamFolderArchiveJobStatus", 
        "DBTEAMTeamFolderArchiveLaunch", 
        "DBTEAMTeamFolderCreateArg", 
        "DBTEAMTeamFolderCreateError", 
        "DBTEAMTeamFolderGetInfoItem", 
        "DBTEAMTeamFolderIdListArg", 
        "DBTEAMTeamFolderInvalidStatusError", 
        "DBTEAMTeamFolderListArg", 
        "DBTEAMTeamFolderListContinueArg", 
        "DBTEAMTeamFolderListContinueError", 
        "DBTEAMTeamFolderListError", 
        "DBTEAMTeamFolderListResult", 
        "DBTEAMTeamFolderMetadata", 
        "DBTEAMTeamFolderPermanentlyDeleteError", 
        "DBTEAMTeamFolderRenameArg", 
        "DBTEAMTeamFolderRenameError", 
        "DBTEAMTeamFolderStatus", 
        "DBTEAMTeamGetInfoResult", 
        "DBTEAMTeamMemberInfo", 
        "DBTEAMTeamMemberProfile", 
        "DBTEAMTeamMemberStatus", 
        "DBTEAMTeamMembershipType", 
        "DBTEAMTokenGetAuthenticatedAdminError", 
        "DBTEAMTokenGetAuthenticatedAdminResult", 
        "DBTEAMUpdatePropertyTemplateArg", 
        "DBTEAMUpdatePropertyTemplateResult", 
        "DBTEAMUploadApiRateLimitValue", 
        "DBTEAMUserSelectorArg", 
        "DBTEAMUsersSelectorArg"
      ]
    }, 
    {
      "name": "TeamCommon", 
      "children": [
        "DBTEAMCOMMONGroupManagementType", 
        "DBTEAMCOMMONGroupSummary", 
        "DBTEAMCOMMONGroupType", 
        "DBTEAMCOMMONTimeRange"
      ]
    }, 
    {
      "name": "TeamLog", 
      "children": [
        "DBTEAMLOGAccessMethodLogInfo", 
        "DBTEAMLOGAccountCaptureChangeAvailabilityDetails", 
        "DBTEAMLOGAccountCaptureChangePolicyDetails", 
        "DBTEAMLOGAccountCaptureMigrateAccountDetails", 
        "DBTEAMLOGAccountCapturePolicy", 
        "DBTEAMLOGAccountCaptureRelinquishAccountDetails", 
        "DBTEAMLOGActorLogInfo", 
        "DBTEAMLOGAllowDownloadDisabledDetails", 
        "DBTEAMLOGAllowDownloadEnabledDetails", 
        "DBTEAMLOGApiSessionLogInfo", 
        "DBTEAMLOGAppLinkTeamDetails", 
        "DBTEAMLOGAppLinkUserDetails", 
        "DBTEAMLOGAppLogInfo", 
        "DBTEAMLOGAppUnlinkTeamDetails", 
        "DBTEAMLOGAppUnlinkUserDetails", 
        "DBTEAMLOGAssetLogInfo", 
        "DBTEAMLOGCollectionShareDetails", 
        "DBTEAMLOGConfidentiality", 
        "DBTEAMLOGContextLogInfo", 
        "DBTEAMLOGCreateFolderDetails", 
        "DBTEAMLOGDataPlacementRestrictionChangePolicyDetails", 
        "DBTEAMLOGDataPlacementRestrictionSatisfyPolicyDetails", 
        "DBTEAMLOGSessionLogInfo", 
        "DBTEAMLOGDesktopSessionLogInfo", 
        "DBTEAMLOGDeviceApprovalsChangeDesktopPolicyDetails", 
        "DBTEAMLOGDeviceApprovalsChangeMobilePolicyDetails", 
        "DBTEAMLOGDeviceApprovalsChangeOverageActionDetails", 
        "DBTEAMLOGDeviceApprovalsChangeUnlinkActionDetails", 
        "DBTEAMLOGDeviceApprovalsPolicy", 
        "DBTEAMLOGDeviceApprovalsRolloutPolicy", 
        "DBTEAMLOGDeviceChangeIpDesktopDetails", 
        "DBTEAMLOGDeviceChangeIpMobileDetails", 
        "DBTEAMLOGDeviceChangeIpWebDetails", 
        "DBTEAMLOGDeviceDeleteOnUnlinkFailDetails", 
        "DBTEAMLOGDeviceDeleteOnUnlinkSuccessDetails", 
        "DBTEAMLOGDeviceLinkFailDetails", 
        "DBTEAMLOGDeviceLinkSuccessDetails", 
        "DBTEAMLOGDeviceLogInfo", 
        "DBTEAMLOGDeviceManagementDisabledDetails", 
        "DBTEAMLOGDeviceManagementEnabledDetails", 
        "DBTEAMLOGDeviceType", 
        "DBTEAMLOGDeviceUnlinkDetails", 
        "DBTEAMLOGDeviceUnlinkPolicy", 
        "DBTEAMLOGDisabledDomainInvitesDetails", 
        "DBTEAMLOGDomainInvitesApproveRequestToJoinTeamDetails", 
        "DBTEAMLOGDomainInvitesDeclineRequestToJoinTeamDetails", 
        "DBTEAMLOGDomainInvitesEmailExistingUsersDetails", 
        "DBTEAMLOGDomainInvitesRequestToJoinTeamDetails", 
        "DBTEAMLOGDomainInvitesSetInviteNewUserPrefToNoDetails", 
        "DBTEAMLOGDomainInvitesSetInviteNewUserPrefToYesDetails", 
        "DBTEAMLOGDomainVerificationAddDomainFailDetails", 
        "DBTEAMLOGDomainVerificationAddDomainSuccessDetails", 
        "DBTEAMLOGDomainVerificationRemoveDomainDetails", 
        "DBTEAMLOGEmmAddExceptionDetails", 
        "DBTEAMLOGEmmChangePolicyDetails", 
        "DBTEAMLOGEmmCreateExceptionsReportDetails", 
        "DBTEAMLOGEmmCreateUsageReportDetails", 
        "DBTEAMLOGEmmLoginSuccessDetails", 
        "DBTEAMLOGEmmRefreshAuthTokenDetails", 
        "DBTEAMLOGEmmRemoveExceptionDetails", 
        "DBTEAMLOGEnableDisableChangePolicy", 
        "DBTEAMLOGEnabledDomainInvitesDetails", 
        "DBTEAMLOGEventCategory", 
        "DBTEAMLOGEventDetails", 
        "DBTEAMLOGEventType", 
        "DBTEAMLOGExtendedVersionHistoryChangePolicyDetails", 
        "DBTEAMLOGExtendedVersionHistoryPolicy", 
        "DBTEAMLOGExternalSharingAccessibilityPolicy", 
        "DBTEAMLOGExternalSharingPolicy", 
        "DBTEAMLOGFileAddCommentDetails", 
        "DBTEAMLOGFileAddDetails", 
        "DBTEAMLOGFileCommentsChangePolicyDetails", 
        "DBTEAMLOGFileCopyDetails", 
        "DBTEAMLOGFileDeleteDetails", 
        "DBTEAMLOGFileDownloadDetails", 
        "DBTEAMLOGFileEditDetails", 
        "DBTEAMLOGFileGetCopyReferenceDetails", 
        "DBTEAMLOGFileLikeCommentDetails", 
        "DBTEAMLOGFileOrFolderLogInfo", 
        "DBTEAMLOGFileLogInfo", 
        "DBTEAMLOGFileMoveDetails", 
        "DBTEAMLOGFilePermanentlyDeleteDetails", 
        "DBTEAMLOGFilePreviewDetails", 
        "DBTEAMLOGFileRenameDetails", 
        "DBTEAMLOGFileRequestAddDeadlineDetails", 
        "DBTEAMLOGFileRequestChangeFolderDetails", 
        "DBTEAMLOGFileRequestChangeTitleDetails", 
        "DBTEAMLOGFileRequestCloseDetails", 
        "DBTEAMLOGFileRequestCreateDetails", 
        "DBTEAMLOGFileRequestReceiveFileDetails", 
        "DBTEAMLOGFileRequestRemoveDeadlineDetails", 
        "DBTEAMLOGFileRequestSendDetails", 
        "DBTEAMLOGFileRequestsChangePolicyDetails", 
        "DBTEAMLOGFileRequestsEmailsEnabledDetails", 
        "DBTEAMLOGFileRequestsEmailsRestrictedToTeamOnlyDetails", 
        "DBTEAMLOGFileRestoreDetails", 
        "DBTEAMLOGFileRevertDetails", 
        "DBTEAMLOGFileRollbackChangesDetails", 
        "DBTEAMLOGFileSaveCopyReferenceDetails", 
        "DBTEAMLOGFileUnlikeCommentDetails", 
        "DBTEAMLOGFolderLogInfo", 
        "DBTEAMLOGGeoLocationLogInfo", 
        "DBTEAMLOGGetTeamEventsArg", 
        "DBTEAMLOGGetTeamEventsContinueArg", 
        "DBTEAMLOGGetTeamEventsContinueError", 
        "DBTEAMLOGGetTeamEventsError", 
        "DBTEAMLOGGetTeamEventsResult", 
        "DBTEAMLOGGoogleSsoChangePolicyDetails", 
        "DBTEAMLOGGroupAddExternalIdDetails", 
        "DBTEAMLOGGroupAddMemberDetails", 
        "DBTEAMLOGGroupChangeExternalIdDetails", 
        "DBTEAMLOGGroupChangeManagementTypeDetails", 
        "DBTEAMLOGGroupChangeMemberRoleDetails", 
        "DBTEAMLOGGroupCreateDetails", 
        "DBTEAMLOGGroupDeleteDetails", 
        "DBTEAMLOGGroupDescriptionUpdatedDetails", 
        "DBTEAMLOGGroupJoinPolicy", 
        "DBTEAMLOGGroupJoinPolicyUpdatedDetails", 
        "DBTEAMLOGGroupLogInfo", 
        "DBTEAMLOGGroupManagementType", 
        "DBTEAMLOGGroupMovedDetails", 
        "DBTEAMLOGGroupRemoveExternalIdDetails", 
        "DBTEAMLOGGroupRemoveMemberDetails", 
        "DBTEAMLOGGroupRenameDetails", 
        "DBTEAMLOGGroupUserManagementChangePolicyDetails", 
        "DBTEAMLOGGroupsUserManagementPolicy", 
        "DBTEAMLOGHostLogInfo", 
        "DBTEAMLOGLinkAudience", 
        "DBTEAMLOGLogoutDetails", 
        "DBTEAMLOGMemberAddNameDetails", 
        "DBTEAMLOGMemberChangeEmailDetails", 
        "DBTEAMLOGMemberChangeMembershipTypeDetails", 
        "DBTEAMLOGMemberChangeNameDetails", 
        "DBTEAMLOGMemberChangeRoleDetails", 
        "DBTEAMLOGMemberInviteDetails", 
        "DBTEAMLOGMemberJoinDetails", 
        "DBTEAMLOGMemberLeaveDetails", 
        "DBTEAMLOGMemberPermanentlyDeleteAccountContentsDetails", 
        "DBTEAMLOGMemberRecoverDetails", 
        "DBTEAMLOGMemberRequestsChangePolicy", 
        "DBTEAMLOGMemberRequestsChangePolicyDetails", 
        "DBTEAMLOGMemberSpaceLimitsAddExceptionDetails", 
        "DBTEAMLOGMemberSpaceLimitsChangePolicyDetails", 
        "DBTEAMLOGMemberSpaceLimitsChangeStatusDetails", 
        "DBTEAMLOGMemberSpaceLimitsRemoveExceptionDetails", 
        "DBTEAMLOGMemberSuggestDetails", 
        "DBTEAMLOGMemberSuggestionsChangePolicyDetails", 
        "DBTEAMLOGMemberSuspendDetails", 
        "DBTEAMLOGMemberTransferAccountContentsDetails", 
        "DBTEAMLOGMemberUnsuspendDetails", 
        "DBTEAMLOGMicrosoftOfficeAddinChangePolicyDetails", 
        "DBTEAMLOGMissingDetails", 
        "DBTEAMLOGMobileSessionLogInfo", 
        "DBTEAMLOGNamespaceRelativePathLogInfo", 
        "DBTEAMLOGNetworkControlChangePolicyDetails", 
        "DBTEAMLOGUserLogInfo", 
        "DBTEAMLOGNonTeamMemberLogInfo", 
        "DBTEAMLOGNoteAclInviteOnlyDetails", 
        "DBTEAMLOGNoteAclLinkDetails", 
        "DBTEAMLOGNoteAclTeamLinkDetails", 
        "DBTEAMLOGNoteShareReceiveDetails", 
        "DBTEAMLOGNoteSharedDetails", 
        "DBTEAMLOGOpenNoteSharedDetails", 
        "DBTEAMLOGOptionalChangePolicy", 
        "DBTEAMLOGOriginLogInfo", 
        "DBTEAMLOGPaperAccessType", 
        "DBTEAMLOGPaperChangeDeploymentPolicyDetails", 
        "DBTEAMLOGPaperChangeMemberPolicyDetails", 
        "DBTEAMLOGPaperChangePolicyDetails", 
        "DBTEAMLOGPaperContentAddMemberDetails", 
        "DBTEAMLOGPaperContentAddToFolderDetails", 
        "DBTEAMLOGPaperContentArchiveDetails", 
        "DBTEAMLOGPaperContentChangeSubscriptionDetails", 
        "DBTEAMLOGPaperContentCreateDetails", 
        "DBTEAMLOGPaperContentPermanentlyDeleteDetails", 
        "DBTEAMLOGPaperContentRemoveFromFolderDetails", 
        "DBTEAMLOGPaperContentRemoveMemberDetails", 
        "DBTEAMLOGPaperContentRenameDetails", 
        "DBTEAMLOGPaperContentRestoreDetails", 
        "DBTEAMLOGPaperDeploymentPolicy", 
        "DBTEAMLOGPaperDocAddCommentDetails", 
        "DBTEAMLOGPaperDocChangeMemberRoleDetails", 
        "DBTEAMLOGPaperDocChangeSharingPolicyDetails", 
        "DBTEAMLOGPaperDocDeleteCommentDetails", 
        "DBTEAMLOGPaperDocDeletedDetails", 
        "DBTEAMLOGPaperDocDownloadDetails", 
        "DBTEAMLOGPaperDocEditCommentDetails", 
        "DBTEAMLOGPaperDocEditDetails", 
        "DBTEAMLOGPaperDocFollowedDetails", 
        "DBTEAMLOGPaperDocMentionDetails", 
        "DBTEAMLOGPaperDocRequestAccessDetails", 
        "DBTEAMLOGPaperDocResolveCommentDetails", 
        "DBTEAMLOGPaperDocRevertDetails", 
        "DBTEAMLOGPaperDocSlackShareDetails", 
        "DBTEAMLOGPaperDocTeamInviteDetails", 
        "DBTEAMLOGPaperDocUnresolveCommentDetails", 
        "DBTEAMLOGPaperDocViewDetails", 
        "DBTEAMLOGPaperDocumentLogInfo", 
        "DBTEAMLOGPaperDownloadFormat", 
        "DBTEAMLOGPaperEnabledUsersGroupAdditionDetails", 
        "DBTEAMLOGPaperEnabledUsersGroupRemovalDetails", 
        "DBTEAMLOGPaperExternalViewAllowDetails", 
        "DBTEAMLOGPaperExternalViewDefaultTeamDetails", 
        "DBTEAMLOGPaperExternalViewForbidDetails", 
        "DBTEAMLOGPaperFolderDeletedDetails", 
        "DBTEAMLOGPaperFolderFollowedDetails", 
        "DBTEAMLOGPaperFolderLogInfo", 
        "DBTEAMLOGPaperFolderTeamInviteDetails", 
        "DBTEAMLOGPaperTaggedValue", 
        "DBTEAMLOGParticipantLogInfo", 
        "DBTEAMLOGPasswordChangeDetails", 
        "DBTEAMLOGPasswordLoginFailDetails", 
        "DBTEAMLOGPasswordLoginSuccessDetails", 
        "DBTEAMLOGPasswordResetAllDetails", 
        "DBTEAMLOGPasswordResetDetails", 
        "DBTEAMLOGPathLogInfo", 
        "DBTEAMLOGPermanentDeleteChangePolicyDetails", 
        "DBTEAMLOGPlacementRestriction", 
        "DBTEAMLOGRemoveLogoutUrlDetails", 
        "DBTEAMLOGRemoveSsoUrlDetails", 
        "DBTEAMLOGResellerLogInfo", 
        "DBTEAMLOGResellerSupportSessionEndDetails", 
        "DBTEAMLOGResellerSupportSessionStartDetails", 
        "DBTEAMLOGSessionsManagementIdleLengthPolicy", 
        "DBTEAMLOGSessionsManagementSessionLengthPolicy", 
        "DBTEAMLOGSfAddGroupDetails", 
        "DBTEAMLOGSfAllowNonMembersToViewSharedLinksDetails", 
        "DBTEAMLOGSfExternalInviteWarnDetails", 
        "DBTEAMLOGSfInviteGroupDetails", 
        "DBTEAMLOGSfNestDetails", 
        "DBTEAMLOGSfTeamDeclineDetails", 
        "DBTEAMLOGSfTeamGrantAccessDetails", 
        "DBTEAMLOGSfTeamInviteChangeRoleDetails", 
        "DBTEAMLOGSfTeamInviteDetails", 
        "DBTEAMLOGSfTeamJoinDetails", 
        "DBTEAMLOGSfTeamJoinFromOobLinkDetails", 
        "DBTEAMLOGSfTeamUninviteDetails", 
        "DBTEAMLOGSharedContentAddInviteesDetails", 
        "DBTEAMLOGSharedContentAddLinkExpiryDetails", 
        "DBTEAMLOGSharedContentAddLinkPasswordDetails", 
        "DBTEAMLOGSharedContentAddMemberDetails", 
        "DBTEAMLOGSharedContentChangeDownloadsPolicyDetails", 
        "DBTEAMLOGSharedContentChangeInviteeRoleDetails", 
        "DBTEAMLOGSharedContentChangeLinkAudienceDetails", 
        "DBTEAMLOGSharedContentChangeLinkExpiryDetails", 
        "DBTEAMLOGSharedContentChangeLinkPasswordDetails", 
        "DBTEAMLOGSharedContentChangeMemberRoleDetails", 
        "DBTEAMLOGSharedContentChangeViewerInfoPolicyDetails", 
        "DBTEAMLOGSharedContentClaimInvitationDetails", 
        "DBTEAMLOGSharedContentCopyDetails", 
        "DBTEAMLOGSharedContentDownloadDetails", 
        "DBTEAMLOGSharedContentRelinquishMembershipDetails", 
        "DBTEAMLOGSharedContentRemoveInviteeDetails", 
        "DBTEAMLOGSharedContentRemoveLinkExpiryDetails", 
        "DBTEAMLOGSharedContentRemoveLinkPasswordDetails", 
        "DBTEAMLOGSharedContentRemoveMemberDetails", 
        "DBTEAMLOGSharedContentRequestAccessDetails", 
        "DBTEAMLOGSharedContentUnshareDetails", 
        "DBTEAMLOGSharedContentViewDetails", 
        "DBTEAMLOGSharedFolderChangeConfidentialityDetails", 
        "DBTEAMLOGSharedFolderChangeLinkPolicyDetails", 
        "DBTEAMLOGSharedFolderChangeMemberManagementPolicyDetails", 
        "DBTEAMLOGSharedFolderChangeMemberPolicyDetails", 
        "DBTEAMLOGSharedFolderCreateDetails", 
        "DBTEAMLOGSharedFolderLinkPolicy", 
        "DBTEAMLOGSharedFolderLogInfo", 
        "DBTEAMLOGSharedFolderMembershipManagementPolicy", 
        "DBTEAMLOGSharedFolderMountDetails", 
        "DBTEAMLOGSharedFolderTransferOwnershipDetails", 
        "DBTEAMLOGSharedFolderUnmountDetails", 
        "DBTEAMLOGSharedNoteOpenedDetails", 
        "DBTEAMLOGSharingChangeFolderJoinPolicyDetails", 
        "DBTEAMLOGSharingChangeLinkPolicyDetails", 
        "DBTEAMLOGSharingChangeMemberPolicyDetails", 
        "DBTEAMLOGShmodelAppCreateDetails", 
        "DBTEAMLOGShmodelCreateDetails", 
        "DBTEAMLOGShmodelDisableDetails", 
        "DBTEAMLOGShmodelFbShareDetails", 
        "DBTEAMLOGShmodelGroupShareDetails", 
        "DBTEAMLOGShmodelRemoveExpirationDetails", 
        "DBTEAMLOGShmodelSetExpirationDetails", 
        "DBTEAMLOGShmodelTeamCopyDetails", 
        "DBTEAMLOGShmodelTeamDownloadDetails", 
        "DBTEAMLOGShmodelTeamShareDetails", 
        "DBTEAMLOGShmodelTeamViewDetails", 
        "DBTEAMLOGShmodelVisibilityPasswordDetails", 
        "DBTEAMLOGShmodelVisibilityPublicDetails", 
        "DBTEAMLOGShmodelVisibilityTeamOnlyDetails", 
        "DBTEAMLOGSignInAsSessionEndDetails", 
        "DBTEAMLOGSignInAsSessionStartDetails", 
        "DBTEAMLOGSmartSyncChangePolicyDetails", 
        "DBTEAMLOGSmartSyncCreateAdminPrivilegeReportDetails", 
        "DBTEAMLOGSmartSyncPolicy", 
        "DBTEAMLOGSpaceLimitsLevel", 
        "DBTEAMLOGSpaceLimitsStatus", 
        "DBTEAMLOGSsoChangeCertDetails", 
        "DBTEAMLOGSsoChangeLoginUrlDetails", 
        "DBTEAMLOGSsoChangeLogoutUrlDetails", 
        "DBTEAMLOGSsoChangePolicyDetails", 
        "DBTEAMLOGSsoChangeSamlIdentityModeDetails", 
        "DBTEAMLOGSsoLoginFailDetails", 
        "DBTEAMLOGTeamActivityCreateReportDetails", 
        "DBTEAMLOGTeamEvent", 
        "DBTEAMLOGTeamFolderChangeStatusDetails", 
        "DBTEAMLOGTeamFolderCreateDetails", 
        "DBTEAMLOGTeamFolderDowngradeDetails", 
        "DBTEAMLOGTeamFolderPermanentlyDeleteDetails", 
        "DBTEAMLOGTeamFolderRenameDetails", 
        "DBTEAMLOGTeamFolderStatus", 
        "DBTEAMLOGTeamLinkedAppLogInfo", 
        "DBTEAMLOGTeamMemberLogInfo", 
        "DBTEAMLOGTeamMergeDetails", 
        "DBTEAMLOGTeamProfileAddLogoDetails", 
        "DBTEAMLOGTeamProfileChangeLogoDetails", 
        "DBTEAMLOGTeamProfileChangeNameDetails", 
        "DBTEAMLOGTeamProfileRemoveLogoDetails", 
        "DBTEAMLOGTfaAddBackupPhoneDetails", 
        "DBTEAMLOGTfaAddSecurityKeyDetails", 
        "DBTEAMLOGTfaChangeBackupPhoneDetails", 
        "DBTEAMLOGTfaChangePolicyDetails", 
        "DBTEAMLOGTfaChangeStatusDetails", 
        "DBTEAMLOGTfaConfiguration", 
        "DBTEAMLOGTfaRemoveBackupPhoneDetails", 
        "DBTEAMLOGTfaRemoveSecurityKeyDetails", 
        "DBTEAMLOGTfaResetDetails", 
        "DBTEAMLOGTwoAccountChangePolicyDetails", 
        "DBTEAMLOGUserLinkedAppLogInfo", 
        "DBTEAMLOGUserNameLogInfo", 
        "DBTEAMLOGUserOrTeamLinkedAppLogInfo", 
        "DBTEAMLOGWebSessionLogInfo", 
        "DBTEAMLOGWebSessionsChangeFixedLengthPolicyDetails", 
        "DBTEAMLOGWebSessionsChangeIdleLengthPolicyDetails"
      ]
    }, 
    {
      "name": "TeamPolicies", 
      "children": [
        "DBTEAMPOLICIESEmmState", 
        "DBTEAMPOLICIESSharedFolderJoinPolicy", 
        "DBTEAMPOLICIESSharedFolderMemberPolicy", 
        "DBTEAMPOLICIESSharedLinkCreatePolicy", 
        "DBTEAMPOLICIESTeamMemberPolicies", 
        "DBTEAMPOLICIESTeamSharingPolicies"
      ]
    }, 
    {
      "name": "Users", 
      "children": [
        "DBUSERSAccount", 
        "DBUSERSBasicAccount", 
        "DBUSERSFullAccount", 
        "DBUSERSTeam", 
        "DBUSERSFullTeam", 
        "DBUSERSGetAccountArg", 
        "DBUSERSGetAccountBatchArg", 
        "DBUSERSGetAccountBatchError", 
        "DBUSERSGetAccountError", 
        "DBUSERSIndividualSpaceAllocation", 
        "DBUSERSName", 
        "DBUSERSSpaceAllocation", 
        "DBUSERSSpaceUsage", 
        "DBUSERSTeamSpaceAllocation"
      ]
    }, 
    {
      "name": "UsersCommon", 
      "children": [
        "DBUSERSCOMMONAccountType"
      ]
    }, 
    {
      "name": "Clients", 
      "children": [
        "DBUserClient", 
        "DBTeamClient", 
        "DBAppClient", 
        "DBClientsManager"
      ]
    }, 
    {
      "name": "Networking", 
      "children": [
        "DBTask", 
        "DBRpcTask", 
        "DBUploadTask", 
        "DBDownloadUrlTask", 
        "DBDownloadDataTask", 
        "DBRequestError", 
        "DBRequestHttpError", 
        "DBRequestBadInputError", 
        "DBRequestAuthError", 
        "DBRequestAccessError", 
        "DBRequestRateLimitError", 
        "DBRequestInternalServerError", 
        "DBRequestClientError", 
        "DBTransportBaseConfig", 
        "DBTransportDefaultConfig", 
        "DBGlobalErrorResponseHandler", 
        "DBTransportBaseClient", 
        "DBTransportDefaultClient", 
        "DBProgressBlock", 
        "DBBatchUploadResponseBlock", 
        "DBTasksStorage"
      ]
    }, 
    {
      "name": "Custom", 
      "children": [
        "DBBatchUploadData", 
        "DBBatchUploadTask"
      ]
    }, 
    {
      "name": "OAuth", 
      "children": [
        "DBOAuthMobileManager", 
        "DBOAuthManager", 
        "DBAccessToken", 
        "DBOAuthResult", 
        "DBMobileSharedApplication", 
        "DBDesktopSharedApplication", 
        "DBSharedApplication"
      ]
    }, 
    {
      "name": "Serializers", 
      "children": [
        "DBArraySerializer", 
        "DBNSDateSerializer", 
        "DBASYNCLaunchResultBaseSerializer", 
        "DBASYNCLaunchEmptyResultSerializer", 
        "DBASYNCPollArgSerializer", 
        "DBASYNCPollResultBaseSerializer", 
        "DBASYNCPollEmptyResultSerializer", 
        "DBASYNCPollErrorSerializer", 
        "DBAUTHAccessErrorSerializer", 
        "DBAUTHAuthErrorSerializer", 
        "DBAUTHInvalidAccountTypeErrorSerializer", 
        "DBAUTHPaperAccessErrorSerializer", 
        "DBAUTHRateLimitErrorSerializer", 
        "DBAUTHRateLimitReasonSerializer", 
        "DBAUTHTokenFromOAuth1ArgSerializer", 
        "DBAUTHTokenFromOAuth1ErrorSerializer", 
        "DBAUTHTokenFromOAuth1ResultSerializer", 
        "DBCOMMONInvalidPathRootErrorSerializer", 
        "DBCOMMONPathRootSerializer", 
        "DBCOMMONPathRootErrorSerializer", 
        "DBFILESPropertiesErrorSerializer", 
        "DBFILESInvalidPropertyGroupErrorSerializer", 
        "DBFILESAddPropertiesErrorSerializer", 
        "DBFILESGetMetadataArgSerializer", 
        "DBFILESAlphaGetMetadataArgSerializer", 
        "DBFILESGetMetadataErrorSerializer", 
        "DBFILESAlphaGetMetadataErrorSerializer", 
        "DBFILESCommitInfoSerializer", 
        "DBFILESCommitInfoWithPropertiesSerializer", 
        "DBFILESCreateFolderArgSerializer", 
        "DBFILESCreateFolderErrorSerializer", 
        "DBFILESDeleteArgSerializer", 
        "DBFILESDeleteBatchArgSerializer", 
        "DBFILESDeleteBatchErrorSerializer", 
        "DBFILESDeleteBatchJobStatusSerializer", 
        "DBFILESDeleteBatchLaunchSerializer", 
        "DBFILESDeleteBatchResultSerializer", 
        "DBFILESDeleteBatchResultEntrySerializer", 
        "DBFILESDeleteErrorSerializer", 
        "DBFILESDeleteResultSerializer", 
        "DBFILESMetadataSerializer", 
        "DBFILESDeletedMetadataSerializer", 
        "DBFILESDimensionsSerializer", 
        "DBFILESDownloadArgSerializer", 
        "DBFILESDownloadErrorSerializer", 
        "DBFILESFileMetadataSerializer", 
        "DBFILESSharingInfoSerializer", 
        "DBFILESFileSharingInfoSerializer", 
        "DBFILESFolderMetadataSerializer", 
        "DBFILESFolderSharingInfoSerializer", 
        "DBFILESGetCopyReferenceArgSerializer", 
        "DBFILESGetCopyReferenceErrorSerializer", 
        "DBFILESGetCopyReferenceResultSerializer", 
        "DBFILESGetTemporaryLinkArgSerializer", 
        "DBFILESGetTemporaryLinkErrorSerializer", 
        "DBFILESGetTemporaryLinkResultSerializer", 
        "DBFILESGpsCoordinatesSerializer", 
        "DBFILESListFolderArgSerializer", 
        "DBFILESListFolderContinueArgSerializer", 
        "DBFILESListFolderContinueErrorSerializer", 
        "DBFILESListFolderErrorSerializer", 
        "DBFILESListFolderGetLatestCursorResultSerializer", 
        "DBFILESListFolderLongpollArgSerializer", 
        "DBFILESListFolderLongpollErrorSerializer", 
        "DBFILESListFolderLongpollResultSerializer", 
        "DBFILESListFolderResultSerializer", 
        "DBFILESListRevisionsArgSerializer", 
        "DBFILESListRevisionsErrorSerializer", 
        "DBFILESListRevisionsResultSerializer", 
        "DBFILESLookUpPropertiesErrorSerializer", 
        "DBFILESLookupErrorSerializer", 
        "DBFILESMediaInfoSerializer", 
        "DBFILESMediaMetadataSerializer", 
        "DBFILESPhotoMetadataSerializer", 
        "DBFILESPreviewArgSerializer", 
        "DBFILESPreviewErrorSerializer", 
        "DBFILESPropertyGroupUpdateSerializer", 
        "DBFILESPropertyGroupWithPathSerializer", 
        "DBFILESRelocationPathSerializer", 
        "DBFILESRelocationArgSerializer", 
        "DBFILESRelocationBatchArgSerializer", 
        "DBFILESRelocationErrorSerializer", 
        "DBFILESRelocationBatchErrorSerializer", 
        "DBFILESRelocationBatchJobStatusSerializer", 
        "DBFILESRelocationBatchLaunchSerializer", 
        "DBFILESRelocationBatchResultSerializer", 
        "DBFILESRelocationResultSerializer", 
        "DBFILESRemovePropertiesArgSerializer", 
        "DBFILESRemovePropertiesErrorSerializer", 
        "DBFILESRestoreArgSerializer", 
        "DBFILESRestoreErrorSerializer", 
        "DBFILESSaveCopyReferenceArgSerializer", 
        "DBFILESSaveCopyReferenceErrorSerializer", 
        "DBFILESSaveCopyReferenceResultSerializer", 
        "DBFILESSaveUrlArgSerializer", 
        "DBFILESSaveUrlErrorSerializer", 
        "DBFILESSaveUrlJobStatusSerializer", 
        "DBFILESSaveUrlResultSerializer", 
        "DBFILESSearchArgSerializer", 
        "DBFILESSearchErrorSerializer", 
        "DBFILESSearchMatchSerializer", 
        "DBFILESSearchMatchTypeSerializer", 
        "DBFILESSearchModeSerializer", 
        "DBFILESSearchResultSerializer", 
        "DBFILESThumbnailArgSerializer", 
        "DBFILESThumbnailErrorSerializer", 
        "DBFILESThumbnailFormatSerializer", 
        "DBFILESThumbnailSizeSerializer", 
        "DBFILESUpdatePropertiesErrorSerializer", 
        "DBFILESUpdatePropertyGroupArgSerializer", 
        "DBFILESUploadErrorSerializer", 
        "DBFILESUploadErrorWithPropertiesSerializer", 
        "DBFILESUploadSessionAppendArgSerializer", 
        "DBFILESUploadSessionCursorSerializer", 
        "DBFILESUploadSessionFinishArgSerializer", 
        "DBFILESUploadSessionFinishBatchArgSerializer", 
        "DBFILESUploadSessionFinishBatchJobStatusSerializer", 
        "DBFILESUploadSessionFinishBatchLaunchSerializer", 
        "DBFILESUploadSessionFinishBatchResultSerializer", 
        "DBFILESUploadSessionFinishBatchResultEntrySerializer", 
        "DBFILESUploadSessionFinishErrorSerializer", 
        "DBFILESUploadSessionLookupErrorSerializer", 
        "DBFILESUploadSessionOffsetErrorSerializer", 
        "DBFILESUploadSessionStartArgSerializer", 
        "DBFILESUploadSessionStartResultSerializer", 
        "DBFILESUploadWriteFailedSerializer", 
        "DBFILESVideoMetadataSerializer", 
        "DBFILESWriteConflictErrorSerializer", 
        "DBFILESWriteErrorSerializer", 
        "DBFILESWriteModeSerializer", 
        "DBPAPERAddMemberSerializer", 
        "DBPAPERRefPaperDocSerializer", 
        "DBPAPERAddPaperDocUserSerializer", 
        "DBPAPERAddPaperDocUserMemberResultSerializer", 
        "DBPAPERAddPaperDocUserResultSerializer", 
        "DBPAPERCursorSerializer", 
        "DBPAPERPaperApiBaseErrorSerializer", 
        "DBPAPERDocLookupErrorSerializer", 
        "DBPAPERDocSubscriptionLevelSerializer", 
        "DBPAPERExportFormatSerializer", 
        "DBPAPERFolderSerializer", 
        "DBPAPERFolderSharingPolicyTypeSerializer", 
        "DBPAPERFolderSubscriptionLevelSerializer", 
        "DBPAPERFoldersContainingPaperDocSerializer", 
        "DBPAPERInviteeInfoWithPermissionLevelSerializer", 
        "DBPAPERListDocsCursorErrorSerializer", 
        "DBPAPERListPaperDocsArgsSerializer", 
        "DBPAPERListPaperDocsContinueArgsSerializer", 
        "DBPAPERListPaperDocsFilterBySerializer", 
        "DBPAPERListPaperDocsResponseSerializer", 
        "DBPAPERListPaperDocsSortBySerializer", 
        "DBPAPERListPaperDocsSortOrderSerializer", 
        "DBPAPERListUsersCursorErrorSerializer", 
        "DBPAPERListUsersOnFolderArgsSerializer", 
        "DBPAPERListUsersOnFolderContinueArgsSerializer", 
        "DBPAPERListUsersOnFolderResponseSerializer", 
        "DBPAPERListUsersOnPaperDocArgsSerializer", 
        "DBPAPERListUsersOnPaperDocContinueArgsSerializer", 
        "DBPAPERListUsersOnPaperDocResponseSerializer", 
        "DBPAPERPaperApiCursorErrorSerializer", 
        "DBPAPERPaperDocExportSerializer", 
        "DBPAPERPaperDocExportResultSerializer", 
        "DBPAPERPaperDocPermissionLevelSerializer", 
        "DBPAPERPaperDocSharingPolicySerializer", 
        "DBPAPERRemovePaperDocUserSerializer", 
        "DBPAPERSharingPolicySerializer", 
        "DBPAPERSharingTeamPolicyTypeSerializer", 
        "DBPAPERSharingPublicPolicyTypeSerializer", 
        "DBPAPERUserInfoWithPermissionLevelSerializer", 
        "DBPAPERUserOnPaperDocFilterSerializer", 
        "DBPROPERTIESGetPropertyTemplateArgSerializer", 
        "DBPROPERTIESPropertyGroupTemplateSerializer", 
        "DBPROPERTIESGetPropertyTemplateResultSerializer", 
        "DBPROPERTIESListPropertyTemplateIdsSerializer", 
        "DBPROPERTIESPropertyTemplateErrorSerializer", 
        "DBPROPERTIESModifyPropertyTemplateErrorSerializer", 
        "DBPROPERTIESPropertyFieldSerializer", 
        "DBPROPERTIESPropertyFieldTemplateSerializer", 
        "DBPROPERTIESPropertyGroupSerializer", 
        "DBPROPERTIESPropertyTypeSerializer", 
        "DBSHARINGAccessLevelSerializer", 
        "DBSHARINGAclUpdatePolicySerializer", 
        "DBSHARINGAddFileMemberArgsSerializer", 
        "DBSHARINGAddFileMemberErrorSerializer", 
        "DBSHARINGAddFolderMemberArgSerializer", 
        "DBSHARINGAddFolderMemberErrorSerializer", 
        "DBSHARINGAddMemberSerializer", 
        "DBSHARINGAddMemberSelectorErrorSerializer", 
        "DBSHARINGAudienceRestrictingSharedFolderSerializer", 
        "DBSHARINGChangeFileMemberAccessArgsSerializer", 
        "DBSHARINGLinkMetadataSerializer", 
        "DBSHARINGCollectionLinkMetadataSerializer", 
        "DBSHARINGCreateSharedLinkArgSerializer", 
        "DBSHARINGCreateSharedLinkErrorSerializer", 
        "DBSHARINGCreateSharedLinkWithSettingsArgSerializer", 
        "DBSHARINGCreateSharedLinkWithSettingsErrorSerializer", 
        "DBSHARINGSharedContentLinkMetadataBaseSerializer", 
        "DBSHARINGExpectedSharedContentLinkMetadataSerializer", 
        "DBSHARINGFileActionSerializer", 
        "DBSHARINGFileErrorResultSerializer", 
        "DBSHARINGSharedLinkMetadataSerializer", 
        "DBSHARINGFileLinkMetadataSerializer", 
        "DBSHARINGFileMemberActionErrorSerializer", 
        "DBSHARINGFileMemberActionIndividualResultSerializer", 
        "DBSHARINGFileMemberActionResultSerializer", 
        "DBSHARINGFileMemberRemoveActionResultSerializer", 
        "DBSHARINGFilePermissionSerializer", 
        "DBSHARINGFolderActionSerializer", 
        "DBSHARINGFolderLinkMetadataSerializer", 
        "DBSHARINGFolderPermissionSerializer", 
        "DBSHARINGFolderPolicySerializer", 
        "DBSHARINGGetFileMetadataArgSerializer", 
        "DBSHARINGGetFileMetadataBatchArgSerializer", 
        "DBSHARINGGetFileMetadataBatchResultSerializer", 
        "DBSHARINGGetFileMetadataErrorSerializer", 
        "DBSHARINGGetFileMetadataIndividualResultSerializer", 
        "DBSHARINGGetMetadataArgsSerializer", 
        "DBSHARINGSharedLinkErrorSerializer", 
        "DBSHARINGGetSharedLinkFileErrorSerializer", 
        "DBSHARINGGetSharedLinkMetadataArgSerializer", 
        "DBSHARINGGetSharedLinksArgSerializer", 
        "DBSHARINGGetSharedLinksErrorSerializer", 
        "DBSHARINGGetSharedLinksResultSerializer", 
        "DBSHARINGGroupInfoSerializer", 
        "DBSHARINGMembershipInfoSerializer", 
        "DBSHARINGGroupMembershipInfoSerializer", 
        "DBSHARINGInsufficientQuotaAmountsSerializer", 
        "DBSHARINGInviteeInfoSerializer", 
        "DBSHARINGInviteeMembershipInfoSerializer", 
        "DBSHARINGJobErrorSerializer", 
        "DBSHARINGJobStatusSerializer", 
        "DBSHARINGLinkActionSerializer", 
        "DBSHARINGLinkAudienceSerializer", 
        "DBSHARINGLinkExpirySerializer", 
        "DBSHARINGLinkPasswordSerializer", 
        "DBSHARINGLinkPermissionSerializer", 
        "DBSHARINGLinkPermissionsSerializer", 
        "DBSHARINGLinkSettingsSerializer", 
        "DBSHARINGListFileMembersArgSerializer", 
        "DBSHARINGListFileMembersBatchArgSerializer", 
        "DBSHARINGListFileMembersBatchResultSerializer", 
        "DBSHARINGListFileMembersContinueArgSerializer", 
        "DBSHARINGListFileMembersContinueErrorSerializer", 
        "DBSHARINGListFileMembersCountResultSerializer", 
        "DBSHARINGListFileMembersErrorSerializer", 
        "DBSHARINGListFileMembersIndividualResultSerializer", 
        "DBSHARINGListFilesArgSerializer", 
        "DBSHARINGListFilesContinueArgSerializer", 
        "DBSHARINGListFilesContinueErrorSerializer", 
        "DBSHARINGListFilesResultSerializer", 
        "DBSHARINGListFolderMembersCursorArgSerializer", 
        "DBSHARINGListFolderMembersArgsSerializer", 
        "DBSHARINGListFolderMembersContinueArgSerializer", 
        "DBSHARINGListFolderMembersContinueErrorSerializer", 
        "DBSHARINGListFoldersArgsSerializer", 
        "DBSHARINGListFoldersContinueArgSerializer", 
        "DBSHARINGListFoldersContinueErrorSerializer", 
        "DBSHARINGListFoldersResultSerializer", 
        "DBSHARINGListSharedLinksArgSerializer", 
        "DBSHARINGListSharedLinksErrorSerializer", 
        "DBSHARINGListSharedLinksResultSerializer", 
        "DBSHARINGMemberAccessLevelResultSerializer", 
        "DBSHARINGMemberActionSerializer", 
        "DBSHARINGMemberPermissionSerializer", 
        "DBSHARINGMemberPolicySerializer", 
        "DBSHARINGMemberSelectorSerializer", 
        "DBSHARINGModifySharedLinkSettingsArgsSerializer", 
        "DBSHARINGModifySharedLinkSettingsErrorSerializer", 
        "DBSHARINGMountFolderArgSerializer", 
        "DBSHARINGMountFolderErrorSerializer", 
        "DBSHARINGParentFolderAccessInfoSerializer", 
        "DBSHARINGPathLinkMetadataSerializer", 
        "DBSHARINGPendingUploadModeSerializer", 
        "DBSHARINGPermissionDeniedReasonSerializer", 
        "DBSHARINGRelinquishFileMembershipArgSerializer", 
        "DBSHARINGRelinquishFileMembershipErrorSerializer", 
        "DBSHARINGRelinquishFolderMembershipArgSerializer", 
        "DBSHARINGRelinquishFolderMembershipErrorSerializer", 
        "DBSHARINGRemoveFileMemberArgSerializer", 
        "DBSHARINGRemoveFileMemberErrorSerializer", 
        "DBSHARINGRemoveFolderMemberArgSerializer", 
        "DBSHARINGRemoveFolderMemberErrorSerializer", 
        "DBSHARINGRemoveMemberJobStatusSerializer", 
        "DBSHARINGRequestedVisibilitySerializer", 
        "DBSHARINGResolvedVisibilitySerializer", 
        "DBSHARINGRevokeSharedLinkArgSerializer", 
        "DBSHARINGRevokeSharedLinkErrorSerializer", 
        "DBSHARINGShareFolderArgSerializer", 
        "DBSHARINGShareFolderErrorBaseSerializer", 
        "DBSHARINGShareFolderErrorSerializer", 
        "DBSHARINGShareFolderJobStatusSerializer", 
        "DBSHARINGShareFolderLaunchSerializer", 
        "DBSHARINGSharePathErrorSerializer", 
        "DBSHARINGSharedContentLinkMetadataSerializer", 
        "DBSHARINGSharedFileMembersSerializer", 
        "DBSHARINGSharedFileMetadataSerializer", 
        "DBSHARINGSharedFolderAccessErrorSerializer", 
        "DBSHARINGSharedFolderMemberErrorSerializer", 
        "DBSHARINGSharedFolderMembersSerializer", 
        "DBSHARINGSharedFolderMetadataBaseSerializer", 
        "DBSHARINGSharedFolderMetadataSerializer", 
        "DBSHARINGSharedLinkAccessFailureReasonSerializer", 
        "DBSHARINGSharedLinkPolicySerializer", 
        "DBSHARINGSharedLinkSettingsSerializer", 
        "DBSHARINGSharedLinkSettingsErrorSerializer", 
        "DBSHARINGSharingFileAccessErrorSerializer", 
        "DBSHARINGSharingUserErrorSerializer", 
        "DBSHARINGTeamMemberInfoSerializer", 
        "DBSHARINGTransferFolderArgSerializer", 
        "DBSHARINGTransferFolderErrorSerializer", 
        "DBSHARINGUnmountFolderArgSerializer", 
        "DBSHARINGUnmountFolderErrorSerializer", 
        "DBSHARINGUnshareFileArgSerializer", 
        "DBSHARINGUnshareFileErrorSerializer", 
        "DBSHARINGUnshareFolderArgSerializer", 
        "DBSHARINGUnshareFolderErrorSerializer", 
        "DBSHARINGUpdateFileMemberArgsSerializer", 
        "DBSHARINGUpdateFolderMemberArgSerializer", 
        "DBSHARINGUpdateFolderMemberErrorSerializer", 
        "DBSHARINGUpdateFolderPolicyArgSerializer", 
        "DBSHARINGUpdateFolderPolicyErrorSerializer", 
        "DBSHARINGUserInfoSerializer", 
        "DBSHARINGUserMembershipInfoSerializer", 
        "DBSHARINGViewerInfoPolicySerializer", 
        "DBSHARINGVisibilitySerializer", 
        "DBTEAMDeviceSessionSerializer", 
        "DBTEAMActiveWebSessionSerializer", 
        "DBTEAMAddPropertyTemplateArgSerializer", 
        "DBTEAMAddPropertyTemplateResultSerializer", 
        "DBTEAMAdminTierSerializer", 
        "DBTEAMApiAppSerializer", 
        "DBTEAMBaseDfbReportSerializer", 
        "DBTEAMBaseTeamFolderErrorSerializer", 
        "DBTEAMDateRangeSerializer", 
        "DBTEAMDateRangeErrorSerializer", 
        "DBTEAMDesktopClientSessionSerializer", 
        "DBTEAMDesktopPlatformSerializer", 
        "DBTEAMDeviceSessionArgSerializer", 
        "DBTEAMDevicesActiveSerializer", 
        "DBTEAMFeatureSerializer", 
        "DBTEAMFeatureValueSerializer", 
        "DBTEAMFeaturesGetValuesBatchArgSerializer", 
        "DBTEAMFeaturesGetValuesBatchErrorSerializer", 
        "DBTEAMFeaturesGetValuesBatchResultSerializer", 
        "DBTEAMGetActivityReportSerializer", 
        "DBTEAMGetDevicesReportSerializer", 
        "DBTEAMGetMembershipReportSerializer", 
        "DBTEAMGetStorageReportSerializer", 
        "DBTEAMGroupAccessTypeSerializer", 
        "DBTEAMGroupCreateArgSerializer", 
        "DBTEAMGroupCreateErrorSerializer", 
        "DBTEAMGroupSelectorErrorSerializer", 
        "DBTEAMGroupSelectorWithTeamGroupErrorSerializer", 
        "DBTEAMGroupDeleteErrorSerializer", 
        "DBTEAMGroupFullInfoSerializer", 
        "DBTEAMGroupMemberInfoSerializer", 
        "DBTEAMGroupMemberSelectorSerializer", 
        "DBTEAMGroupMemberSelectorErrorSerializer", 
        "DBTEAMGroupMemberSetAccessTypeErrorSerializer", 
        "DBTEAMIncludeMembersArgSerializer", 
        "DBTEAMGroupMembersAddArgSerializer", 
        "DBTEAMGroupMembersAddErrorSerializer", 
        "DBTEAMGroupMembersChangeResultSerializer", 
        "DBTEAMGroupMembersRemoveArgSerializer", 
        "DBTEAMGroupMembersSelectorErrorSerializer", 
        "DBTEAMGroupMembersRemoveErrorSerializer", 
        "DBTEAMGroupMembersSelectorSerializer", 
        "DBTEAMGroupMembersSetAccessTypeArgSerializer", 
        "DBTEAMGroupSelectorSerializer", 
        "DBTEAMGroupUpdateArgsSerializer", 
        "DBTEAMGroupUpdateErrorSerializer", 
        "DBTEAMGroupsGetInfoErrorSerializer", 
        "DBTEAMGroupsGetInfoItemSerializer", 
        "DBTEAMGroupsListArgSerializer", 
        "DBTEAMGroupsListContinueArgSerializer", 
        "DBTEAMGroupsListContinueErrorSerializer", 
        "DBTEAMGroupsListResultSerializer", 
        "DBTEAMGroupsMembersListArgSerializer", 
        "DBTEAMGroupsMembersListContinueArgSerializer", 
        "DBTEAMGroupsMembersListContinueErrorSerializer", 
        "DBTEAMGroupsMembersListResultSerializer", 
        "DBTEAMGroupsPollErrorSerializer", 
        "DBTEAMGroupsSelectorSerializer", 
        "DBTEAMListMemberAppsArgSerializer", 
        "DBTEAMListMemberAppsErrorSerializer", 
        "DBTEAMListMemberAppsResultSerializer", 
        "DBTEAMListMemberDevicesArgSerializer", 
        "DBTEAMListMemberDevicesErrorSerializer", 
        "DBTEAMListMemberDevicesResultSerializer", 
        "DBTEAMListMembersAppsArgSerializer", 
        "DBTEAMListMembersAppsErrorSerializer", 
        "DBTEAMListMembersAppsResultSerializer", 
        "DBTEAMListMembersDevicesArgSerializer", 
        "DBTEAMListMembersDevicesErrorSerializer", 
        "DBTEAMListMembersDevicesResultSerializer", 
        "DBTEAMListTeamAppsArgSerializer", 
        "DBTEAMListTeamAppsErrorSerializer", 
        "DBTEAMListTeamAppsResultSerializer", 
        "DBTEAMListTeamDevicesArgSerializer", 
        "DBTEAMListTeamDevicesErrorSerializer", 
        "DBTEAMListTeamDevicesResultSerializer", 
        "DBTEAMMemberAccessSerializer", 
        "DBTEAMMemberAddArgSerializer", 
        "DBTEAMMemberAddResultSerializer", 
        "DBTEAMMemberDevicesSerializer", 
        "DBTEAMMemberLinkedAppsSerializer", 
        "DBTEAMMemberProfileSerializer", 
        "DBTEAMUserSelectorErrorSerializer", 
        "DBTEAMMemberSelectorErrorSerializer", 
        "DBTEAMMembersAddArgSerializer", 
        "DBTEAMMembersAddJobStatusSerializer", 
        "DBTEAMMembersAddLaunchSerializer", 
        "DBTEAMMembersDeactivateArgSerializer", 
        "DBTEAMMembersDeactivateErrorSerializer", 
        "DBTEAMMembersGetInfoArgsSerializer", 
        "DBTEAMMembersGetInfoErrorSerializer", 
        "DBTEAMMembersGetInfoItemSerializer", 
        "DBTEAMMembersListArgSerializer", 
        "DBTEAMMembersListContinueArgSerializer", 
        "DBTEAMMembersListContinueErrorSerializer", 
        "DBTEAMMembersListErrorSerializer", 
        "DBTEAMMembersListResultSerializer", 
        "DBTEAMMembersRecoverArgSerializer", 
        "DBTEAMMembersRecoverErrorSerializer", 
        "DBTEAMMembersRemoveArgSerializer", 
        "DBTEAMMembersRemoveErrorSerializer", 
        "DBTEAMMembersSendWelcomeErrorSerializer", 
        "DBTEAMMembersSetPermissionsArgSerializer", 
        "DBTEAMMembersSetPermissionsErrorSerializer", 
        "DBTEAMMembersSetPermissionsResultSerializer", 
        "DBTEAMMembersSetProfileArgSerializer", 
        "DBTEAMMembersSetProfileErrorSerializer", 
        "DBTEAMMembersSuspendErrorSerializer", 
        "DBTEAMMembersUnsuspendArgSerializer", 
        "DBTEAMMembersUnsuspendErrorSerializer", 
        "DBTEAMMobileClientPlatformSerializer", 
        "DBTEAMMobileClientSessionSerializer", 
        "DBTEAMRemovedStatusSerializer", 
        "DBTEAMRevokeDesktopClientArgSerializer", 
        "DBTEAMRevokeDeviceSessionArgSerializer", 
        "DBTEAMRevokeDeviceSessionBatchArgSerializer", 
        "DBTEAMRevokeDeviceSessionBatchErrorSerializer", 
        "DBTEAMRevokeDeviceSessionBatchResultSerializer", 
        "DBTEAMRevokeDeviceSessionErrorSerializer", 
        "DBTEAMRevokeDeviceSessionStatusSerializer", 
        "DBTEAMRevokeLinkedApiAppArgSerializer", 
        "DBTEAMRevokeLinkedApiAppBatchArgSerializer", 
        "DBTEAMRevokeLinkedAppBatchErrorSerializer", 
        "DBTEAMRevokeLinkedAppBatchResultSerializer", 
        "DBTEAMRevokeLinkedAppErrorSerializer", 
        "DBTEAMRevokeLinkedAppStatusSerializer", 
        "DBTEAMStorageBucketSerializer", 
        "DBTEAMTeamFolderAccessErrorSerializer", 
        "DBTEAMTeamFolderActivateErrorSerializer", 
        "DBTEAMTeamFolderIdArgSerializer", 
        "DBTEAMTeamFolderArchiveArgSerializer", 
        "DBTEAMTeamFolderArchiveErrorSerializer", 
        "DBTEAMTeamFolderArchiveJobStatusSerializer", 
        "DBTEAMTeamFolderArchiveLaunchSerializer", 
        "DBTEAMTeamFolderCreateArgSerializer", 
        "DBTEAMTeamFolderCreateErrorSerializer", 
        "DBTEAMTeamFolderGetInfoItemSerializer", 
        "DBTEAMTeamFolderIdListArgSerializer", 
        "DBTEAMTeamFolderInvalidStatusErrorSerializer", 
        "DBTEAMTeamFolderListArgSerializer", 
        "DBTEAMTeamFolderListContinueArgSerializer", 
        "DBTEAMTeamFolderListContinueErrorSerializer", 
        "DBTEAMTeamFolderListErrorSerializer", 
        "DBTEAMTeamFolderListResultSerializer", 
        "DBTEAMTeamFolderMetadataSerializer", 
        "DBTEAMTeamFolderPermanentlyDeleteErrorSerializer", 
        "DBTEAMTeamFolderRenameArgSerializer", 
        "DBTEAMTeamFolderRenameErrorSerializer", 
        "DBTEAMTeamFolderStatusSerializer", 
        "DBTEAMTeamGetInfoResultSerializer", 
        "DBTEAMTeamMemberInfoSerializer", 
        "DBTEAMTeamMemberProfileSerializer", 
        "DBTEAMTeamMemberStatusSerializer", 
        "DBTEAMTeamMembershipTypeSerializer", 
        "DBTEAMTokenGetAuthenticatedAdminErrorSerializer", 
        "DBTEAMTokenGetAuthenticatedAdminResultSerializer", 
        "DBTEAMUpdatePropertyTemplateArgSerializer", 
        "DBTEAMUpdatePropertyTemplateResultSerializer", 
        "DBTEAMUploadApiRateLimitValueSerializer", 
        "DBTEAMUserSelectorArgSerializer", 
        "DBTEAMUsersSelectorArgSerializer", 
        "DBTEAMCOMMONGroupManagementTypeSerializer", 
        "DBTEAMCOMMONGroupSummarySerializer", 
        "DBTEAMCOMMONGroupTypeSerializer", 
        "DBTEAMCOMMONTimeRangeSerializer", 
        "DBTEAMLOGAccessMethodLogInfoSerializer", 
        "DBTEAMLOGAccountCaptureChangeAvailabilityDetailsSerializer", 
        "DBTEAMLOGAccountCaptureChangePolicyDetailsSerializer", 
        "DBTEAMLOGAccountCaptureMigrateAccountDetailsSerializer", 
        "DBTEAMLOGAccountCapturePolicySerializer", 
        "DBTEAMLOGAccountCaptureRelinquishAccountDetailsSerializer", 
        "DBTEAMLOGActorLogInfoSerializer", 
        "DBTEAMLOGAllowDownloadDisabledDetailsSerializer", 
        "DBTEAMLOGAllowDownloadEnabledDetailsSerializer", 
        "DBTEAMLOGApiSessionLogInfoSerializer", 
        "DBTEAMLOGAppLinkTeamDetailsSerializer", 
        "DBTEAMLOGAppLinkUserDetailsSerializer", 
        "DBTEAMLOGAppLogInfoSerializer", 
        "DBTEAMLOGAppUnlinkTeamDetailsSerializer", 
        "DBTEAMLOGAppUnlinkUserDetailsSerializer", 
        "DBTEAMLOGAssetLogInfoSerializer", 
        "DBTEAMLOGCollectionShareDetailsSerializer", 
        "DBTEAMLOGConfidentialitySerializer", 
        "DBTEAMLOGContextLogInfoSerializer", 
        "DBTEAMLOGCreateFolderDetailsSerializer", 
        "DBTEAMLOGDataPlacementRestrictionChangePolicyDetailsSerializer", 
        "DBTEAMLOGDataPlacementRestrictionSatisfyPolicyDetailsSerializer", 
        "DBTEAMLOGSessionLogInfoSerializer", 
        "DBTEAMLOGDesktopSessionLogInfoSerializer", 
        "DBTEAMLOGDeviceApprovalsChangeDesktopPolicyDetailsSerializer", 
        "DBTEAMLOGDeviceApprovalsChangeMobilePolicyDetailsSerializer", 
        "DBTEAMLOGDeviceApprovalsChangeOverageActionDetailsSerializer", 
        "DBTEAMLOGDeviceApprovalsChangeUnlinkActionDetailsSerializer", 
        "DBTEAMLOGDeviceApprovalsPolicySerializer", 
        "DBTEAMLOGDeviceApprovalsRolloutPolicySerializer", 
        "DBTEAMLOGDeviceChangeIpDesktopDetailsSerializer", 
        "DBTEAMLOGDeviceChangeIpMobileDetailsSerializer", 
        "DBTEAMLOGDeviceChangeIpWebDetailsSerializer", 
        "DBTEAMLOGDeviceDeleteOnUnlinkFailDetailsSerializer", 
        "DBTEAMLOGDeviceDeleteOnUnlinkSuccessDetailsSerializer", 
        "DBTEAMLOGDeviceLinkFailDetailsSerializer", 
        "DBTEAMLOGDeviceLinkSuccessDetailsSerializer", 
        "DBTEAMLOGDeviceLogInfoSerializer", 
        "DBTEAMLOGDeviceManagementDisabledDetailsSerializer", 
        "DBTEAMLOGDeviceManagementEnabledDetailsSerializer", 
        "DBTEAMLOGDeviceTypeSerializer", 
        "DBTEAMLOGDeviceUnlinkDetailsSerializer", 
        "DBTEAMLOGDeviceUnlinkPolicySerializer", 
        "DBTEAMLOGDisabledDomainInvitesDetailsSerializer", 
        "DBTEAMLOGDomainInvitesApproveRequestToJoinTeamDetailsSerializer", 
        "DBTEAMLOGDomainInvitesDeclineRequestToJoinTeamDetailsSerializer", 
        "DBTEAMLOGDomainInvitesEmailExistingUsersDetailsSerializer", 
        "DBTEAMLOGDomainInvitesRequestToJoinTeamDetailsSerializer", 
        "DBTEAMLOGDomainInvitesSetInviteNewUserPrefToNoDetailsSerializer", 
        "DBTEAMLOGDomainInvitesSetInviteNewUserPrefToYesDetailsSerializer", 
        "DBTEAMLOGDomainVerificationAddDomainFailDetailsSerializer", 
        "DBTEAMLOGDomainVerificationAddDomainSuccessDetailsSerializer", 
        "DBTEAMLOGDomainVerificationRemoveDomainDetailsSerializer", 
        "DBTEAMLOGEmmAddExceptionDetailsSerializer", 
        "DBTEAMLOGEmmChangePolicyDetailsSerializer", 
        "DBTEAMLOGEmmCreateExceptionsReportDetailsSerializer", 
        "DBTEAMLOGEmmCreateUsageReportDetailsSerializer", 
        "DBTEAMLOGEmmLoginSuccessDetailsSerializer", 
        "DBTEAMLOGEmmRefreshAuthTokenDetailsSerializer", 
        "DBTEAMLOGEmmRemoveExceptionDetailsSerializer", 
        "DBTEAMLOGEnableDisableChangePolicySerializer", 
        "DBTEAMLOGEnabledDomainInvitesDetailsSerializer", 
        "DBTEAMLOGEventCategorySerializer", 
        "DBTEAMLOGEventDetailsSerializer", 
        "DBTEAMLOGEventTypeSerializer", 
        "DBTEAMLOGExtendedVersionHistoryChangePolicyDetailsSerializer", 
        "DBTEAMLOGExtendedVersionHistoryPolicySerializer", 
        "DBTEAMLOGExternalSharingAccessibilityPolicySerializer", 
        "DBTEAMLOGExternalSharingPolicySerializer", 
        "DBTEAMLOGFileAddCommentDetailsSerializer", 
        "DBTEAMLOGFileAddDetailsSerializer", 
        "DBTEAMLOGFileCommentsChangePolicyDetailsSerializer", 
        "DBTEAMLOGFileCopyDetailsSerializer", 
        "DBTEAMLOGFileDeleteDetailsSerializer", 
        "DBTEAMLOGFileDownloadDetailsSerializer", 
        "DBTEAMLOGFileEditDetailsSerializer", 
        "DBTEAMLOGFileGetCopyReferenceDetailsSerializer", 
        "DBTEAMLOGFileLikeCommentDetailsSerializer", 
        "DBTEAMLOGFileOrFolderLogInfoSerializer", 
        "DBTEAMLOGFileLogInfoSerializer", 
        "DBTEAMLOGFileMoveDetailsSerializer", 
        "DBTEAMLOGFilePermanentlyDeleteDetailsSerializer", 
        "DBTEAMLOGFilePreviewDetailsSerializer", 
        "DBTEAMLOGFileRenameDetailsSerializer", 
        "DBTEAMLOGFileRequestAddDeadlineDetailsSerializer", 
        "DBTEAMLOGFileRequestChangeFolderDetailsSerializer", 
        "DBTEAMLOGFileRequestChangeTitleDetailsSerializer", 
        "DBTEAMLOGFileRequestCloseDetailsSerializer", 
        "DBTEAMLOGFileRequestCreateDetailsSerializer", 
        "DBTEAMLOGFileRequestReceiveFileDetailsSerializer", 
        "DBTEAMLOGFileRequestRemoveDeadlineDetailsSerializer", 
        "DBTEAMLOGFileRequestSendDetailsSerializer", 
        "DBTEAMLOGFileRequestsChangePolicyDetailsSerializer", 
        "DBTEAMLOGFileRequestsEmailsEnabledDetailsSerializer", 
        "DBTEAMLOGFileRequestsEmailsRestrictedToTeamOnlyDetailsSerializer", 
        "DBTEAMLOGFileRestoreDetailsSerializer", 
        "DBTEAMLOGFileRevertDetailsSerializer", 
        "DBTEAMLOGFileRollbackChangesDetailsSerializer", 
        "DBTEAMLOGFileSaveCopyReferenceDetailsSerializer", 
        "DBTEAMLOGFileUnlikeCommentDetailsSerializer", 
        "DBTEAMLOGFolderLogInfoSerializer", 
        "DBTEAMLOGGeoLocationLogInfoSerializer", 
        "DBTEAMLOGGetTeamEventsArgSerializer", 
        "DBTEAMLOGGetTeamEventsContinueArgSerializer", 
        "DBTEAMLOGGetTeamEventsContinueErrorSerializer", 
        "DBTEAMLOGGetTeamEventsErrorSerializer", 
        "DBTEAMLOGGetTeamEventsResultSerializer", 
        "DBTEAMLOGGoogleSsoChangePolicyDetailsSerializer", 
        "DBTEAMLOGGroupAddExternalIdDetailsSerializer", 
        "DBTEAMLOGGroupAddMemberDetailsSerializer", 
        "DBTEAMLOGGroupChangeExternalIdDetailsSerializer", 
        "DBTEAMLOGGroupChangeManagementTypeDetailsSerializer", 
        "DBTEAMLOGGroupChangeMemberRoleDetailsSerializer", 
        "DBTEAMLOGGroupCreateDetailsSerializer", 
        "DBTEAMLOGGroupDeleteDetailsSerializer", 
        "DBTEAMLOGGroupDescriptionUpdatedDetailsSerializer", 
        "DBTEAMLOGGroupJoinPolicySerializer", 
        "DBTEAMLOGGroupJoinPolicyUpdatedDetailsSerializer", 
        "DBTEAMLOGGroupLogInfoSerializer", 
        "DBTEAMLOGGroupManagementTypeSerializer", 
        "DBTEAMLOGGroupMovedDetailsSerializer", 
        "DBTEAMLOGGroupRemoveExternalIdDetailsSerializer", 
        "DBTEAMLOGGroupRemoveMemberDetailsSerializer", 
        "DBTEAMLOGGroupRenameDetailsSerializer", 
        "DBTEAMLOGGroupUserManagementChangePolicyDetailsSerializer", 
        "DBTEAMLOGGroupsUserManagementPolicySerializer", 
        "DBTEAMLOGHostLogInfoSerializer", 
        "DBTEAMLOGLinkAudienceSerializer", 
        "DBTEAMLOGLogoutDetailsSerializer", 
        "DBTEAMLOGMemberAddNameDetailsSerializer", 
        "DBTEAMLOGMemberChangeEmailDetailsSerializer", 
        "DBTEAMLOGMemberChangeMembershipTypeDetailsSerializer", 
        "DBTEAMLOGMemberChangeNameDetailsSerializer", 
        "DBTEAMLOGMemberChangeRoleDetailsSerializer", 
        "DBTEAMLOGMemberInviteDetailsSerializer", 
        "DBTEAMLOGMemberJoinDetailsSerializer", 
        "DBTEAMLOGMemberLeaveDetailsSerializer", 
        "DBTEAMLOGMemberPermanentlyDeleteAccountContentsDetailsSerializer", 
        "DBTEAMLOGMemberRecoverDetailsSerializer", 
        "DBTEAMLOGMemberRequestsChangePolicySerializer", 
        "DBTEAMLOGMemberRequestsChangePolicyDetailsSerializer", 
        "DBTEAMLOGMemberSpaceLimitsAddExceptionDetailsSerializer", 
        "DBTEAMLOGMemberSpaceLimitsChangePolicyDetailsSerializer", 
        "DBTEAMLOGMemberSpaceLimitsChangeStatusDetailsSerializer", 
        "DBTEAMLOGMemberSpaceLimitsRemoveExceptionDetailsSerializer", 
        "DBTEAMLOGMemberSuggestDetailsSerializer", 
        "DBTEAMLOGMemberSuggestionsChangePolicyDetailsSerializer", 
        "DBTEAMLOGMemberSuspendDetailsSerializer", 
        "DBTEAMLOGMemberTransferAccountContentsDetailsSerializer", 
        "DBTEAMLOGMemberUnsuspendDetailsSerializer", 
        "DBTEAMLOGMicrosoftOfficeAddinChangePolicyDetailsSerializer", 
        "DBTEAMLOGMissingDetailsSerializer", 
        "DBTEAMLOGMobileSessionLogInfoSerializer", 
        "DBTEAMLOGNamespaceRelativePathLogInfoSerializer", 
        "DBTEAMLOGNetworkControlChangePolicyDetailsSerializer", 
        "DBTEAMLOGUserLogInfoSerializer", 
        "DBTEAMLOGNonTeamMemberLogInfoSerializer", 
        "DBTEAMLOGNoteAclInviteOnlyDetailsSerializer", 
        "DBTEAMLOGNoteAclLinkDetailsSerializer", 
        "DBTEAMLOGNoteAclTeamLinkDetailsSerializer", 
        "DBTEAMLOGNoteShareReceiveDetailsSerializer", 
        "DBTEAMLOGNoteSharedDetailsSerializer", 
        "DBTEAMLOGOpenNoteSharedDetailsSerializer", 
        "DBTEAMLOGOptionalChangePolicySerializer", 
        "DBTEAMLOGOriginLogInfoSerializer", 
        "DBTEAMLOGPaperAccessTypeSerializer", 
        "DBTEAMLOGPaperChangeDeploymentPolicyDetailsSerializer", 
        "DBTEAMLOGPaperChangeMemberPolicyDetailsSerializer", 
        "DBTEAMLOGPaperChangePolicyDetailsSerializer", 
        "DBTEAMLOGPaperContentAddMemberDetailsSerializer", 
        "DBTEAMLOGPaperContentAddToFolderDetailsSerializer", 
        "DBTEAMLOGPaperContentArchiveDetailsSerializer", 
        "DBTEAMLOGPaperContentChangeSubscriptionDetailsSerializer", 
        "DBTEAMLOGPaperContentCreateDetailsSerializer", 
        "DBTEAMLOGPaperContentPermanentlyDeleteDetailsSerializer", 
        "DBTEAMLOGPaperContentRemoveFromFolderDetailsSerializer", 
        "DBTEAMLOGPaperContentRemoveMemberDetailsSerializer", 
        "DBTEAMLOGPaperContentRenameDetailsSerializer", 
        "DBTEAMLOGPaperContentRestoreDetailsSerializer", 
        "DBTEAMLOGPaperDeploymentPolicySerializer", 
        "DBTEAMLOGPaperDocAddCommentDetailsSerializer", 
        "DBTEAMLOGPaperDocChangeMemberRoleDetailsSerializer", 
        "DBTEAMLOGPaperDocChangeSharingPolicyDetailsSerializer", 
        "DBTEAMLOGPaperDocDeleteCommentDetailsSerializer", 
        "DBTEAMLOGPaperDocDeletedDetailsSerializer", 
        "DBTEAMLOGPaperDocDownloadDetailsSerializer", 
        "DBTEAMLOGPaperDocEditCommentDetailsSerializer", 
        "DBTEAMLOGPaperDocEditDetailsSerializer", 
        "DBTEAMLOGPaperDocFollowedDetailsSerializer", 
        "DBTEAMLOGPaperDocMentionDetailsSerializer", 
        "DBTEAMLOGPaperDocRequestAccessDetailsSerializer", 
        "DBTEAMLOGPaperDocResolveCommentDetailsSerializer", 
        "DBTEAMLOGPaperDocRevertDetailsSerializer", 
        "DBTEAMLOGPaperDocSlackShareDetailsSerializer", 
        "DBTEAMLOGPaperDocTeamInviteDetailsSerializer", 
        "DBTEAMLOGPaperDocUnresolveCommentDetailsSerializer", 
        "DBTEAMLOGPaperDocViewDetailsSerializer", 
        "DBTEAMLOGPaperDocumentLogInfoSerializer", 
        "DBTEAMLOGPaperDownloadFormatSerializer", 
        "DBTEAMLOGPaperEnabledUsersGroupAdditionDetailsSerializer", 
        "DBTEAMLOGPaperEnabledUsersGroupRemovalDetailsSerializer", 
        "DBTEAMLOGPaperExternalViewAllowDetailsSerializer", 
        "DBTEAMLOGPaperExternalViewDefaultTeamDetailsSerializer", 
        "DBTEAMLOGPaperExternalViewForbidDetailsSerializer", 
        "DBTEAMLOGPaperFolderDeletedDetailsSerializer", 
        "DBTEAMLOGPaperFolderFollowedDetailsSerializer", 
        "DBTEAMLOGPaperFolderLogInfoSerializer", 
        "DBTEAMLOGPaperFolderTeamInviteDetailsSerializer", 
        "DBTEAMLOGPaperTaggedValueSerializer", 
        "DBTEAMLOGParticipantLogInfoSerializer", 
        "DBTEAMLOGPasswordChangeDetailsSerializer", 
        "DBTEAMLOGPasswordLoginFailDetailsSerializer", 
        "DBTEAMLOGPasswordLoginSuccessDetailsSerializer", 
        "DBTEAMLOGPasswordResetAllDetailsSerializer", 
        "DBTEAMLOGPasswordResetDetailsSerializer", 
        "DBTEAMLOGPathLogInfoSerializer", 
        "DBTEAMLOGPermanentDeleteChangePolicyDetailsSerializer", 
        "DBTEAMLOGPlacementRestrictionSerializer", 
        "DBTEAMLOGRemoveLogoutUrlDetailsSerializer", 
        "DBTEAMLOGRemoveSsoUrlDetailsSerializer", 
        "DBTEAMLOGResellerLogInfoSerializer", 
        "DBTEAMLOGResellerSupportSessionEndDetailsSerializer", 
        "DBTEAMLOGResellerSupportSessionStartDetailsSerializer", 
        "DBTEAMLOGSessionsManagementIdleLengthPolicySerializer", 
        "DBTEAMLOGSessionsManagementSessionLengthPolicySerializer", 
        "DBTEAMLOGSfAddGroupDetailsSerializer", 
        "DBTEAMLOGSfAllowNonMembersToViewSharedLinksDetailsSerializer", 
        "DBTEAMLOGSfExternalInviteWarnDetailsSerializer", 
        "DBTEAMLOGSfInviteGroupDetailsSerializer", 
        "DBTEAMLOGSfNestDetailsSerializer", 
        "DBTEAMLOGSfTeamDeclineDetailsSerializer", 
        "DBTEAMLOGSfTeamGrantAccessDetailsSerializer", 
        "DBTEAMLOGSfTeamInviteChangeRoleDetailsSerializer", 
        "DBTEAMLOGSfTeamInviteDetailsSerializer", 
        "DBTEAMLOGSfTeamJoinDetailsSerializer", 
        "DBTEAMLOGSfTeamJoinFromOobLinkDetailsSerializer", 
        "DBTEAMLOGSfTeamUninviteDetailsSerializer", 
        "DBTEAMLOGSharedContentAddInviteesDetailsSerializer", 
        "DBTEAMLOGSharedContentAddLinkExpiryDetailsSerializer", 
        "DBTEAMLOGSharedContentAddLinkPasswordDetailsSerializer", 
        "DBTEAMLOGSharedContentAddMemberDetailsSerializer", 
        "DBTEAMLOGSharedContentChangeDownloadsPolicyDetailsSerializer", 
        "DBTEAMLOGSharedContentChangeInviteeRoleDetailsSerializer", 
        "DBTEAMLOGSharedContentChangeLinkAudienceDetailsSerializer", 
        "DBTEAMLOGSharedContentChangeLinkExpiryDetailsSerializer", 
        "DBTEAMLOGSharedContentChangeLinkPasswordDetailsSerializer", 
        "DBTEAMLOGSharedContentChangeMemberRoleDetailsSerializer", 
        "DBTEAMLOGSharedContentChangeViewerInfoPolicyDetailsSerializer", 
        "DBTEAMLOGSharedContentClaimInvitationDetailsSerializer", 
        "DBTEAMLOGSharedContentCopyDetailsSerializer", 
        "DBTEAMLOGSharedContentDownloadDetailsSerializer", 
        "DBTEAMLOGSharedContentRelinquishMembershipDetailsSerializer", 
        "DBTEAMLOGSharedContentRemoveInviteeDetailsSerializer", 
        "DBTEAMLOGSharedContentRemoveLinkExpiryDetailsSerializer", 
        "DBTEAMLOGSharedContentRemoveLinkPasswordDetailsSerializer", 
        "DBTEAMLOGSharedContentRemoveMemberDetailsSerializer", 
        "DBTEAMLOGSharedContentRequestAccessDetailsSerializer", 
        "DBTEAMLOGSharedContentUnshareDetailsSerializer", 
        "DBTEAMLOGSharedContentViewDetailsSerializer", 
        "DBTEAMLOGSharedFolderChangeConfidentialityDetailsSerializer", 
        "DBTEAMLOGSharedFolderChangeLinkPolicyDetailsSerializer", 
        "DBTEAMLOGSharedFolderChangeMemberManagementPolicyDetailsSerializer", 
        "DBTEAMLOGSharedFolderChangeMemberPolicyDetailsSerializer", 
        "DBTEAMLOGSharedFolderCreateDetailsSerializer", 
        "DBTEAMLOGSharedFolderLinkPolicySerializer", 
        "DBTEAMLOGSharedFolderLogInfoSerializer", 
        "DBTEAMLOGSharedFolderMembershipManagementPolicySerializer", 
        "DBTEAMLOGSharedFolderMountDetailsSerializer", 
        "DBTEAMLOGSharedFolderTransferOwnershipDetailsSerializer", 
        "DBTEAMLOGSharedFolderUnmountDetailsSerializer", 
        "DBTEAMLOGSharedNoteOpenedDetailsSerializer", 
        "DBTEAMLOGSharingChangeFolderJoinPolicyDetailsSerializer", 
        "DBTEAMLOGSharingChangeLinkPolicyDetailsSerializer", 
        "DBTEAMLOGSharingChangeMemberPolicyDetailsSerializer", 
        "DBTEAMLOGShmodelAppCreateDetailsSerializer", 
        "DBTEAMLOGShmodelCreateDetailsSerializer", 
        "DBTEAMLOGShmodelDisableDetailsSerializer", 
        "DBTEAMLOGShmodelFbShareDetailsSerializer", 
        "DBTEAMLOGShmodelGroupShareDetailsSerializer", 
        "DBTEAMLOGShmodelRemoveExpirationDetailsSerializer", 
        "DBTEAMLOGShmodelSetExpirationDetailsSerializer", 
        "DBTEAMLOGShmodelTeamCopyDetailsSerializer", 
        "DBTEAMLOGShmodelTeamDownloadDetailsSerializer", 
        "DBTEAMLOGShmodelTeamShareDetailsSerializer", 
        "DBTEAMLOGShmodelTeamViewDetailsSerializer", 
        "DBTEAMLOGShmodelVisibilityPasswordDetailsSerializer", 
        "DBTEAMLOGShmodelVisibilityPublicDetailsSerializer", 
        "DBTEAMLOGShmodelVisibilityTeamOnlyDetailsSerializer", 
        "DBTEAMLOGSignInAsSessionEndDetailsSerializer", 
        "DBTEAMLOGSignInAsSessionStartDetailsSerializer", 
        "DBTEAMLOGSmartSyncChangePolicyDetailsSerializer", 
        "DBTEAMLOGSmartSyncCreateAdminPrivilegeReportDetailsSerializer", 
        "DBTEAMLOGSmartSyncPolicySerializer", 
        "DBTEAMLOGSpaceLimitsLevelSerializer", 
        "DBTEAMLOGSpaceLimitsStatusSerializer", 
        "DBTEAMLOGSsoChangeCertDetailsSerializer", 
        "DBTEAMLOGSsoChangeLoginUrlDetailsSerializer", 
        "DBTEAMLOGSsoChangeLogoutUrlDetailsSerializer", 
        "DBTEAMLOGSsoChangePolicyDetailsSerializer", 
        "DBTEAMLOGSsoChangeSamlIdentityModeDetailsSerializer", 
        "DBTEAMLOGSsoLoginFailDetailsSerializer", 
        "DBTEAMLOGTeamActivityCreateReportDetailsSerializer", 
        "DBTEAMLOGTeamEventSerializer", 
        "DBTEAMLOGTeamFolderChangeStatusDetailsSerializer", 
        "DBTEAMLOGTeamFolderCreateDetailsSerializer", 
        "DBTEAMLOGTeamFolderDowngradeDetailsSerializer", 
        "DBTEAMLOGTeamFolderPermanentlyDeleteDetailsSerializer", 
        "DBTEAMLOGTeamFolderRenameDetailsSerializer", 
        "DBTEAMLOGTeamFolderStatusSerializer", 
        "DBTEAMLOGTeamLinkedAppLogInfoSerializer", 
        "DBTEAMLOGTeamMemberLogInfoSerializer", 
        "DBTEAMLOGTeamMergeDetailsSerializer", 
        "DBTEAMLOGTeamProfileAddLogoDetailsSerializer", 
        "DBTEAMLOGTeamProfileChangeLogoDetailsSerializer", 
        "DBTEAMLOGTeamProfileChangeNameDetailsSerializer", 
        "DBTEAMLOGTeamProfileRemoveLogoDetailsSerializer", 
        "DBTEAMLOGTfaAddBackupPhoneDetailsSerializer", 
        "DBTEAMLOGTfaAddSecurityKeyDetailsSerializer", 
        "DBTEAMLOGTfaChangeBackupPhoneDetailsSerializer", 
        "DBTEAMLOGTfaChangePolicyDetailsSerializer", 
        "DBTEAMLOGTfaChangeStatusDetailsSerializer", 
        "DBTEAMLOGTfaConfigurationSerializer", 
        "DBTEAMLOGTfaRemoveBackupPhoneDetailsSerializer", 
        "DBTEAMLOGTfaRemoveSecurityKeyDetailsSerializer", 
        "DBTEAMLOGTfaResetDetailsSerializer", 
        "DBTEAMLOGTwoAccountChangePolicyDetailsSerializer", 
        "DBTEAMLOGUserLinkedAppLogInfoSerializer", 
        "DBTEAMLOGUserNameLogInfoSerializer", 
        "DBTEAMLOGUserOrTeamLinkedAppLogInfoSerializer", 
        "DBTEAMLOGWebSessionLogInfoSerializer", 
        "DBTEAMLOGWebSessionsChangeFixedLengthPolicyDetailsSerializer", 
        "DBTEAMLOGWebSessionsChangeIdleLengthPolicyDetailsSerializer", 
        "DBTEAMPOLICIESEmmStateSerializer", 
        "DBTEAMPOLICIESSharedFolderJoinPolicySerializer", 
        "DBTEAMPOLICIESSharedFolderMemberPolicySerializer", 
        "DBTEAMPOLICIESSharedLinkCreatePolicySerializer", 
        "DBTEAMPOLICIESTeamMemberPoliciesSerializer", 
        "DBTEAMPOLICIESTeamSharingPoliciesSerializer", 
        "DBUSERSAccountSerializer", 
        "DBUSERSBasicAccountSerializer", 
        "DBUSERSFullAccountSerializer", 
        "DBUSERSTeamSerializer", 
        "DBUSERSFullTeamSerializer", 
        "DBUSERSGetAccountArgSerializer", 
        "DBUSERSGetAccountBatchArgSerializer", 
        "DBUSERSGetAccountBatchErrorSerializer", 
        "DBUSERSGetAccountErrorSerializer", 
        "DBUSERSIndividualSpaceAllocationSerializer", 
        "DBUSERSNameSerializer", 
        "DBUSERSSpaceAllocationSerializer", 
        "DBUSERSSpaceUsageSerializer", 
        "DBUSERSTeamSpaceAllocationSerializer", 
        "DBUSERSCOMMONAccountTypeSerializer"
      ]
    }, 
    {
      "name": "Union Tags", 
      "children": [
        "DBOAuthErrorType", 
        "DBOAuthResultTag", 
        "DBRequestErrorTag"
      ]
    }, 
    {
      "name": "Route Objects", 
      "children": []
    }
  ], 
  "author_url": "https://dropbox.com/developers", 
  "hide_documentation_coverage": true
}
